{"THE\n": 1, "JOHN F. KENNEDY\n": 1, "CtNvas\n": 1, "Tue\n": 1, "UITEE\n": 1, "STD\n": 1, "Floryan\n": 1, "OES\n": 1, "Pert\n": 1, "RELEASE\n": 1, "CUSTODIAL\n": 1, "IF\n": 1, "DATE Riv\n": 1, "PRINT\n": 1, "SIGNATURE OF\n": 1, "MEN Oe\n": 1, "UNA\n": 1, "aCeNE\n": 1, "ATL\n": 1, "Boreal\n": 1, "DATE\n": 1, "Nal Se\n": 1, "bethMita\n": 1, "Beene Genrncnebeane\n": 1, "clitaCo\n": 1, "J\n": 1, "SECRET\n": 1, "Phen Filiod\n": 1, "Gare REQUEST FOR\n": 1, "PERSONNEL\n": 1, "SEATAL\n": 1, "MATURE\n": 1, "PERSONNEL ACTION\n": 1, "CEFECTIVE\n": 1, "DATE ORGANEZATIONGL\n": 1, "COST\n": 1, "Coanats B\n": 1, "LEsaL\n": 1, "POSITION\n": 1, "OCCUPATIONAL\n": 1, "CAEP\n": 1, "FaPIRES\n": 1, "OPFTCE\n": 1, "BELOW\n": 1, "Sauamy OR Le\n": 1, "RATE 9950\n": 1, "Stento UY\n": 1, "USE\n": 1, "THE Pee\n": 1, "Oars Jythas\u00e9 Toot Yo\n": 1, "Les\n": 1, "CONTROL Imeee\n": 1, "VtS2a\n": 1, "Sioetal\n": 1, "Pome Cat\n": 1, "DATA\n": 1, "afO\n": 1, "XC\n": 1, "FERN\n": 1, "AL\n": 1, "COLOR\n": 1, "Dall Da\n": 1, "Ray\n": 1, "SIGNED\n": 1, "PERSONNEL DATE\n": 1, "Fuge\n": 1, "tecsleeD\n": 1, "SEL\n": 1, "Qala NG\n": 1, "Tas PS\n": 1, "Dtapes\n": 1, "CEATIFIC\n": 1, "DV\n": 1, "MCA Lanny\n": 1, "Comm\n": 1, "Bi M. Collins\n": 1, "S Ta CH\n": 1, "OF\n": 1, "Seaman MP Data\n": 1, "CCvTVETAT\n": 1, "Peter Onk\n": 1, "PeEVtOuUS\n": 1, "OFFECEAL\n": 1, "SPEC\n": 1, "US\n": 1, "POPFeACecG\n": 1, "Toy OL\n": 1, "ATE\n": 1, "ACTIGN\n": 1, "Frei Ge Cove\n": 1, "SERVICE\n": 1, "D ANO\n": 1, "STEP Racorded Csrp\n": 1, "Compisted\n": 1, "CAREER\n": 1, "OPS\n": 1, "CLASSIFICATION\n": 1, "SCHEDULE\n": 1, "GS\n": 1, "LB\n": 1, "MEXICO\n": 1, "MEXICO auTMonI\n": 1, "DERIGNATIONS\n": 1, "Paqrarto\n": 1, "SPL Neel\n": 1, "SECRET AP\n": 1, "SECRET Shen Filled\n": 1, "LB SttaL\n": 1, "PERSONNEL waTuRe OF\n": 1, "ORTH\n": 1, "CATECOSY\n": 1, "Cuaron\n": 1, "EMPLOYMENT\n": 1, "cosT\n": 1, "CENTER\n": 1, "OAGAMIZATIOWAL\n": 1, "EFFECTIVE\n": 1, "DATE FUNDS\n": 1, "SULY\n": 1, "Completed Offic\n": 1, "Personnel\n": 1, "CONCH\n": 1, "MEXICO Frexrceo\n": 1, "Positron\n": 1, "OPS LB\n": 1, "OCCURAT\n": 1, "SALES\n": 1, "STEP\n": 1, "SESVICE Sataev\n": 1, "EES\n": 1, "REMARKS\n": 1, "SECURITY OF\n": 1, "DIVISTON\n": 1, "BANGKOK\n": 1, "OATE\n": 1, "SIGNATURE\n": 1, "SPACE\n": 1, "EMP\n": 1, "TS\n": 1, "ET\n": 1, "OUERFOL\n": 1, "Care\n": 1, "LeNZ\n": 1, "ROM\n": 1, "BME\n": 1, "CRPACEAL\n": 1, "Dale\n": 1, "GrOserT\n": 1, "Tat\n": 1, "DEG\n": 1, "tL\n": 1, "LZIIGI\n": 1, "THe Bs\n": 1, "OATA\n": 1, "Tv Lesetrong\n": 1, "SECMITE\n": 1, "APPROVAL\n": 1, "Son\n": 1, "Ory EOD\n": 1, "MC\n": 1, "UGE\n": 1, "CERTIFICATION\n": 1, "BMC Fr Tart\n": 1, "Oa\n": 1, "GORA\n": 1, "SorstEh\n": 1, "Shame\n": 1, "OTe\n": 1, "Cagtee Catiocar\n": 1, "Data C008\n": 1, "Le Oa\n": 1, "Bab SFL\n": 1, "FOR\n": 1, "USE OF\n": 1, "STATO\n": 1, "ORE\n": 1, "ELIHU\n": 1, "DATE APPROVED Kye\n": 1, "SECRET Vee\n": 1, "SECRET J\n": 1, "EMPLOYER\n": 1, "NAME\n": 1, "ANO\n": 1, "Benefits\n": 1, "Services Bivist\u00e9n\n": 1, "File\n": 1, "Personnel Disability\n": 1, "Austen\n": 1, "Date\n": 1, "Ones\n": 1, "Official Disability\n": 1, "Folder Claim\n": 1, "OFFICIAL\n": 1, "DISABILITY\n": 1, "SECRET Moxec\n": 1, "Se\n": 1, "Aone\n": 1, "Po\n": 1, "Bede Tog\n": 1, "FER Be\n": 1, "STAVDARD\n": 1, "First\n": 1, "mTagtel\n": 1, "ERVECE\n": 1, "SIGNATURE Da\n": 1, "Lee Vetere\n": 1, "DATE Bescon\n": 1, "CREDITABLE\n": 1, "E NOTICE\n": 1, "CONFIDENTIAL Mv\n": 1, "JOH Le\n": 1, "TRANSACTIONS\n": 1, "BRANCH\n": 1, "MERCER\n": 1, "Boe\n": 1, "WOR\n": 1, "LAR\n": 1, "Sony\n": 1, "Lonea\n": 1, "WIT\n": 1, "UATED\n": 1, "PUBLIC\n": 1, "ADJUSTED\n": 1, "GReST\n": 1, "SERTAL\n": 1, "ORGN\n": 1, "FLiryAn Re Kaarys Pook\n": 1, "Teee\n": 1, "Saws\n": 1, "ETRE\n": 1, "POR\n": 1, "Sonn Ma\n": 1, "Grode OLD Stage\n": 1, "Sotary\n": 1, "NO\n": 1, "EXCESS\n": 1, "INITIALS Elective\n": 1, "Cosmas Frenous\n": 1, "PAY\n": 1, "TONS\n": 1, "Pee AUDITED\n": 1, "Ct NAMED\n": 1, "EMPLOYEE\n": 1, "TYPE\n": 1, "THE WORK OF\n": 1, "OF SIGNATURES\n": 1, "PAY END OF\n": 1, "TESTE\n": 1, "EES Mee\n": 1, "AWOP Hours\n": 1, "Autentcoton Remarks\n": 1, "MEW\n": 1, "Step\n": 1, "Soe\n": 1, "AEE\n": 1, "SAAR\n": 1, "eT Cate\n": 1, "OCB\n": 1, "SECRET Filled Tn\n": 1, "NOTIFICATION OF\n": 1, "FFRICTIVE\n": 1, "BRANCH CATEGORY OF EMPLOYETNT\n": 1, "COST CHARGEABLE\n": 1, "GOC\n": 1, "AOTEORITY\n": 1, "ORGANIZATIONAL\n": 1, "Larry\n": 1, "Florygn\n": 1, "WATORE OF\n": 1, "PERSONNEL REASS\n": 1, "ACTION\n": 1, "LAST\n": 1, "SeRtat\n": 1, "TE\n": 1, "POSIEION\n": 1, "MEXICO MEXICO\n": 1, "MEXICO SERVE\n": 1, "MuMsER\n": 1, "OccupATTOnAY Gina\n": 1, "CLASSIFICATION U0\n": 1, "GRADE Ad\n": 1, "SPACE THE\n": 1, "CODE Code\n": 1, "ATE EXPERES\n": 1, "SPECIAL\n": 1, "MELLITUS\n": 1, "STATION\n": 1, "ihTtGREE\n": 1, "aePHaperic\n": 1, "RICA\n": 1, "NONE\n": 1, "MPLAB\n": 1, "LEAVE\n": 1, "Fost Bas\n": 1, "WEALT\n": 1, "CoUk\n": 1, "TAM\n": 1, "ROLL\n": 1, "Secs\n": 1, "NEALIAE\n": 1, "FEDEOAL\n": 1, "ERG\n": 1, "OF B8tf OF\n": 1, "SEAVICE\n": 1, "NCR\n": 1, "DATA SAMAK\n": 1, "Dara Toes\n": 1, "OAIE OF\n": 1, "LONG\n": 1, "GATE\n": 1, "CAREER RECIREMEHT\n": 1, "VEL\n": 1, "SESY\n": 1, "COMP\n": 1, "DATE UOCATION OF\n": 1, "STATION STATE Tax\n": 1, "Fokm ELECT\n": 1, "SIGHATURE\n": 1, "FILEone\n": 1, "CoP Gendag\n": 1, "Filed\n": 1, "SECRET Filled\n": 1, "NOTIFIGATION OF\n": 1, "PERSONNEL SERIAL\n": 1, "LAST Fits\n": 1, "MATURE OF\n": 1, "PLRSONNEL\n": 1, "DATE CATEGORY OF\n": 1, "DOP\n": 1, "GRGAMIZATIONAL\n": 1, "STATION POSITION\n": 1, "OPS MEXICO\n": 1, "StEP\n": 1, "UBL\n": 1, "OCCUPATIONAL MEXICO\n": 1, "RUMRER\n": 1, "CUASSIFICATION\n": 1, "LB MEXICO\n": 1, "LOCATION OF\n": 1, "OFFICIAL MEXICO\n": 1, "CSC\n": 1, "BRANCH COST\n": 1, "CORIEM\n": 1, "CHARGEABLE\n": 1, "SALARY\n": 1, "Remanns\n": 1, "SPECIAL FTE\n": 1, "COMP MERVITE\n": 1, "CESS\n": 1, "BREA\n": 1, "AIR\n": 1, "Fermoy\n": 1, "COR So\n": 1, "Veo Pr\n": 1, "Tee Dt\n": 1, "Security\n": 1, "SECURITY\n": 1, "CODE\n": 1, "STATE\n": 1, "LOD\n": 1, "PHO\n": 1, "TTY\n": 1, "Lehi\n": 1, "INSURANCE\n": 1, "CODE DATE\n": 1, "REQ\n": 1, "OTHER\n": 1, "FEDERAL\n": 1, "CATEGORY\n": 1, "eSv\n": 1, "OATE OF\n": 1, "ETE\n": 1, "OUM\n": 1, "Pee\n": 1, "NO BURea\n": 1, "COMP BATE\n": 1, "DATE PREVIOUS\n": 1, "usoO7s\n": 1, "oNONe\n": 1, "Cope\n": 1, "FOR THE\n": 1, "PERSONNEL INTEGREE\n": 1, "Nagim\n": 1, "OATE OF ALPMADETIC\n": 1, "J EY\n": 1, "Narees\n": 1, "Peon\n": 1, "Cal\n": 1, "PPL Herkabe\n": 1, "Weed\n": 1, "RNa\n": 1, "SECRET FITNESS\n": 1, "NaAME\n": 1, "Leet\n": 1, "FICIAL\n": 1, "Fireo\n": 1, "GENERAL\n": 1, "OATE OF BIRTH\n": 1, "Ops Officer\n": 1, "OF See\n": 1, "CURRENT\n": 1, "Mexico City\n": 1, "Frum\n": 1, "Section\n": 1, "REPORT\n": 1, "CHECK\n": 1, "AP\n": 1, "TEMPOR\n": 1, "TYPE OF\n": 1, "DATE Strong Performance\n": 1, "Porformance\n": 1, "Bris\n": 1, "Porformonce\n": 1, "Parformance\n": 1, "SPECIFIC\n": 1, "List\n": 1, "Insert\n": 1, "CACH\n": 1, "Canrider\n": 1, "MUST\n": 1, "Case Officer\n": 1, "Soviet\n": 1, "SPRCIFIC\n": 1, "lLerren Analyst\n": 1, "Soviet SPUC\n": 1, "SPECIEIE\n": 1, "OVERALL Inte\n": 1, "Tche\n": 1, "CURRENT Fis\n": 1, "Poe\n": 1, "aNoe\n": 1, "LRGE\n": 1, "POSITION TT\n": 1, "Atl PAaVIDWS\n": 1, "SECRET RATING\n": 1, "LETTER Ruasian\n": 1, "SPECIFIC English\n": 1, "SPECIFIC SECRET\n": 1, "SECTION Filled\n": 1, "NARRATIVE\n": 1, "COMMENTS\n": 1, "State\n": 1, "Amplify\n": 1, "Section Manner\n": 1, "Gubject\n": 1, "Station\n": 1, "Subject\n": 1, "Bubject\n": 1, "Station Soviet\n": 1, "Subject Soviet\n": 1, "Soviet Subject\n": 1, "SECTION\n": 1, "COMMENTS CERTIFY\n": 1, "HAVE\n": 1, "siGhea Novenbor\n": 1, "OF SUPERVISOR\n": 1, "MON\n": 1, "QREN\n": 1, "EMPLOVEE\n": 1, "OF PED\n": 1, "EXP\n": 1, "SAND\n": 1, "Herbert Manel\n": 1, "COMMENT OF\n": 1, "PPIGIAL\n": 1, "PITAL\n": 1, "MAUR\n": 1, "Seats\n": 1, "SECRET SECRET\n": 1, "tUden Filled Ta\n": 1, "EMPLOYEE FITNESS\n": 1, "GENERAL EDATE OF\n": 1, "POSITION CARE\n": 1, "CHECK See\n": 1, "Section gBmeciat\n": 1, "TYPE OF WE\n": 1, "PORT\n": 1, "REASHIONMENT\n": 1, "Inadeducte\n": 1, "Doscribe\n": 1, "Section Cc Porformance\n": 1, "Specily\n": 1, "PERIOD\n": 1, "Pram Th\n": 1, "DATE SECTION\n": 1, "CURRENT Mexico City\n": 1, "Pasformonce\n": 1, "SRECIFIC\n": 1, "List Insert\n": 1, "EACH\n": 1, "ONLY\n": 1, "MUST Pees SPECIES\n": 1, "Russian\n": 1, "Spanish\n": 1, "GUTY\n": 1, "GUTY SPECS\n": 1, "RATING\n": 1, "LETTER\n": 1, "LOrTions\n": 1, "RATING O38\n": 1, "Ten Fiffed\n": 1, "COMMENTS Fics\n": 1, "Indicote\n": 1, "RRdehip\n": 1, "Stote\n": 1, "Comment\n": 1, "Amplify Subject\n": 1, "Mexico\n": 1, "Line\n": 1, "Station Station\n": 1, "Subject Subject\n": 1, "Sovict\n": 1, "Subject Subject Station\n": 1, "Subject Subject Subject\n": 1, "Station SECTION\n": 1, "COMMENTS MONTHS\n": 1, "HAS\n": 1, "COMMENTS Oars Janery\n": 1, "THIS\n": 1, "OFFICIAL SUPERVISOR\n": 1, "REVIRWING\n": 1, "B\n": 1, "AND\n": 1, "OF PAINTED Habit\n": 1, "SionaATORa\n": 1, "Orer\n": 1, "Iffteer BY\n": 1, "TITLE OF\n": 1, "GericiaAL\n": 1, "SECRET PRINTED\n": 1, "Ve\n": 1, "O1VE\n": 1, "SEEN\n": 1, "HONATURE\n": 1, "None Poole\n": 1, "PGHATUHE\n": 1, "TAPOR\n": 1, "PMSA\n": 1, "Ba\n": 1, "TRIER BELTON\n": 1, "Boba So\n": 1, "REge\n": 1}