{"RELEASE\n": 1, "JOHN F. KENNEDY\n": 1, "MEMORANDUM\n": 1, "THE\n": 1, "RECORD Plan\n": 1, "Cuba\n": 1, "State\n": 1, "Defense Gilpatric\n": 1, "Cyrus Ball\n": 1, "Vance\n": 1, "Douglas Dillon\n": 1, "Ambassador Thompson\n": 1, "General Wheeler\n": 1, "Mr. Donald Wilson\n": 1, "Mr. McGeorge Bundy\n": 1, "Mr. Bromley Smith\n": 1, "Mr. Edwin Martin\n": 1, "Mr. Ted Sorensen\n": 1, "Mr. John\n": 1, "Mr. Bill Moyers\n": 1, "Crimins\n": 1, "Mr. Gordon\n": 1, "Carter\n": 1, "Mr. Mr. George Helms\n": 1, "Ready\n": 1, "Mr.\n": 1, "FitzGerald\n": 1, "OAS\n": 1, "Venezuelan\n": 1, "Canada\n": 1, "Britain\n": 1, "Spain\n": 1, "Italy\n": 1, "Mr. Bundy\n": 1, "Marshall S. Carter Lieutenant General\n": 1, "USA\n": 1, "MEMORANDUM FOR\n": 1, "THE RECORD\n": 1, "White House\n": 1, "State George W. Ball\n": 1, "Alexis Johnson\n": 1, "Ambassador\n": 1, "Large Llewellyn Thompson\n": 1, "Assistant\n": 1, "Affairs Edwin Affairs\n": 1, "John USIA\n": 1, "Chiefs\n": 1, "Treasury\n": 1, "White Coordinator Cuban\n": 1, "Army Cyrus\n": 1, "Donald Department\n": 1, "House\n": 1, "Crimmins\n": 1, "Defense\n": 1, "Gilpatric\n": 1, "Martin\n": 1, "H\n": 1, "Roswell Vance\n": 1, "Wheeler\n": 1, "Wilson\n": 1, "Executive Douglas Dillon\n": 1, "Assistant McGeorge Bundy\n": 1, "Messrs\n": 1, "George\n": 1, "Williams\n": 1, "Gordon Chase\n": 1, "CIA\n": 1, "Helms\n": 1, "Marshall Desmond S\n": 1, "Carter Reedy\n": 1, "Richard FitzGerald\n": 1, "Bundy\n": 1, "Agency Cuban\n": 1, "Cuba Canada\n": 1, "Spain Cuba\n": 1, "Cuban\n": 1, "Cuban Cuba\n": 1, "Matanzas\n": 1, "U.S.\n": 1, "Soviets\n": 1, "Cuba Cuba\n": 1, "General Wheeler Cuban\n": 1, "Cuba General Carter\n": 1, "Cuba Bundy\n": 1, "U.S. Department\n": 1, "Air\n": 1, "Unilateral\n": 1, "Selective\n": 1, "U.S. Florida\n": 1, "No\n": 1, "Bundy Assistant\n": 1, "Martin Comment\n": 1, "Cuba No\n": 1, "U.S. Cuba\n": 1, "Mr. Bundy Kennedy\n": 1, "Miami\n": 1, "Soviets Cubans\n": 1, "OAS Caribbean\n": 1, "Mr. Bundy Venezuela\n": 1, "Venezuelan Helms\n": 1, "Caracas\n": 1, "Martin OAS\n": 1, "OAS Venezuelan\n": 1, "OAS Cuban\n": 1, "Venezuelan Mr. Bundy\n": 1, "Central America\n": 1, "Ball\n": 1, "Department\n": 1, "Cuba Cuba Christmas\n": 1, "Cuba Ball\n": 1, "Department State\n": 1, "American\n": 1, "Department Desmon Special\n": 1, "itzGerald Affairs\n": 1, "THE Discussion\n": 1, "Introduced\n": 1, "Peer\n": 1, "Silva\n": 1, "Station\n": 1, "Saigon\n": 1, "Governmert\n": 1, "Checklist\n": 1, "Bolivia\n": 1, "OPEC\n": 1, "Italians\n": 1, "French\n": 1, "Spinelli\n": 1, "Royalists\n": 1, "Carter Silva Fiasal\n": 1, "Rusk\n": 1, "Soviet\n": 1, "West\n": 1, "Sukarno\n": 1, "South\n": 1, "American Soviets\n": 1, "General Eisenhower\n": 1, "Eisenhower\n": 1, "Robert Kennedy\n": 1, "Kennedy\n": 1, "Kennedy Saigon\n": 1, "Kennedy Jackie\n": 1, "Kennedy Mr. Bundy\n": 1, "General\n": 1, "General Attorney NSC\n": 1, "Bobby\n": 1, "Foreign Aid\n": 1, "Soviet MEMORANDUM\n": 1, "McNamara\n": 1, "Rostow\n": 1, "William\n": 1, "Bundy McGeorge Bundy\n": 1, "Rusk MLF\n": 1, "Eisenhower General Goodpastor\n": 1, "Amb\n": 1, "General Merchant\n": 1, "Rusk MLF Admiral Ricketts\n": 1, "Rusk United States\n": 1, "MLF\n": 1, "MLF Allied\n": 1, "United States\n": 1, "McNamara Hassel\n": 1, "MLF Germans\n": 1, "Rusk MLF McNamara\n": 1, "MLF United States\n": 1, "U.S. Congressional\n": 1, "Democratic\n": 1, "Republican\n": 1, "Senate\n": 1, "House NSC\n": 1, "Soviet Soviet\n": 1, "Soviet Cline\n": 1, "McGeorge\n": 1, "Bundy McCone\n": 1, "Soviet Rostow\n": 1, "Soviet Programs Foreign Economics\n": 1, "Cuba USSR\n": 1, "NATO\n": 1, "Turkey\n": 1, "Greece\n": 1, "South Korea\n": 1, "USSR\n": 1, "Cuba Checklist\n": 1, "USSR LI\n": 1, "Khmer\n": 1, "Serei\n": 1, "Cambodian\n": 1, "Southeast Thailand\n": 1, "Malaysia\n": 1, "Soviet Moscow\n": 1, "India\n": 1, "Warren\n": 1, "Peer Silva\n": 1, "Saigon Ambassador Lodge\n": 1, "Johnson\n": 1, "Diem\n": 1, "Republican Lodge\n": 1, "Lodge\n": 1, "Bundy Lodge\n": 1, "Eisenhower Lodge\n": 1, "David\n": 1, "South CIA\n": 1, "Smith\n": 1, "Station MEMORANDUM\n": 1, "Dec\n": 1, "RECORD Discussion\n": 1, "Venezuela\n": 1, "Chenault\n": 1, "CIA Bonn\n": 1, "UN Commission\n": 1, "Saigon U.S.\n": 1, "Mexico Briefly\n": 1, "Business Council\n": 1, "SST\n": 1, "Halaby\n": 1, "Bundy Memorandums Conversation\n": 1, "Heads\n": 1, "State Department\n": 1, "Mr. Cline\n": 1, "Bundy Dallas\n": 1, "MEMORANDUM FOR THE\n": 1, "RECORD\n": 1, "DISTRIBUTION\n": 1, "Bundy Johnson\n": 1, "Celebrezze\n": 1, "Johnson Sargent Shriver\n": 1, "Bundy Kennedy\n": 1, "Ayub\n": 1, "Ball Ayub\n": 1, "Embassy\n": 1, "Bundy Ball\n": 1, "Ball Pakistan\n": 1, "Ayub Latin America\n": 1, "Progress\n": 1, "Moscoso\n": 1, "OAS Ward\n": 1, "Allen\n": 1, "OAS Johnson\n": 1, "Mr. Bundy Checklist\n": 1, "Colonel\n": 1, "Chennault\n": 1, "Venezuelan Checklist\n": 1, "Cuba Bundy Cuban\n": 1, "Kennedy Venezuela\n": 1, "Cuba OAS\n": 1, "Khrushchev\n": 1, "OAS USSR\n": 1, "WH\n": 1, "Caribbean\n": 1, "OAS Soviets\n": 1, "Mexico Cuba\n": 1, "CAS Reference\n": 1, "Oswald\n": 1, "Alvarado\n": 1, "Review Board\n": 1, "Oswald Pakistan\n": 1, "Bundy Pakistan\n": 1, "Ayub General Taylor\n": 1, "Taylor\n": 1, "United States Bundy\n": 1, "Pakistan\n": 1, "India Pakistan\n": 1, "Ayub India\n": 1, "USIB\n": 1, "Cuban Reviewed\n": 1, "TACKLE China\n": 1, "COMOR\n": 1, "Special Group\n": 1, "Indians\n": 1, "Takhli\n": 1, "Pakistan Thailand\n": 1, "CORONA\n": 1, "CORONA Veneaul\n": 1, "Group\n": 1, "Carter Mexico City\n": 1, "Oswald Silvia\n": 1, "Oswald USSR\n": 1, "Havana\n": 1, "Silvia Duran\n": 1, "FBI\n": 1, "Ambassador Mann\n": 1, "Nicaraguan\n": 1, "Alvarado Washington\n": 1, "Mexico City\n": 1, "CIA Mexican\n": 1, "FBI CIA\n": 1, "FBI Soest\n": 1, "Mexico City Alvarado\n": 1, "Oswald Cuban\n": 1, "DCI\n": 1, "Secty\n": 1, "McNamara Bundy\n": 1, "Embassy FOR\n": 1, "Johnson Checklist\n": 1, "Venezuelan South Vietnam\n": 1, "Congressional\n": 1, "South Vietnam\n": 1, "Lodge Senate\n": 1, "American ETS\n": 1, "Item\n": 1, "Check\n": 1, "New York Times\n": 1, "New York\n": 1, "American Item\n": 1, "India Israel\n": 1, "USSR Burma\n": 1, "Greece Karamanlis\n": 1, "Karamanlis\n": 1, "Brazil\n": 1, "Inonu\n": 1, "Turkey Colby\n": 1, "Indonesia\n": 1, "Macapagal\n": 1, "Indonesia Malayasia\n": 1, "Cuba Cuba Castro\n": 1, "Cuban Rumanian\n": 1, "Ferguson\n": 1, "Moscow\n": 1, "Moscow Rumanian\n": 1, "Soviet Union\n": 1, "Tito\n": 1, "Ambassador Yugoslavia\n": 1, "Khrushchev Republican\n": 1, "Tito Yugoslavia\n": 1, "Yugoslavia\n": 1, "South Vietnam Hill\n": 1, "Joint Committee\n": 1, "Senator Russell\n": 1, "Committee\n": 1, "Fulbright\n": 1, "Hickenlooper\n": 1, "Vinson\n": 1, "Committee House\n": 1, "Affairs Committee\n": 1, "Russell\n": 1, "OXCART\n": 1, "Defense CIA\n": 1, "Kennedy McNamara\n": 1, "Kennedy Johnson\n": 1, "McNamara Rusk\n": 1, "Bundy State\n": 1, "Check List\n": 1, "Bulletin\n": 1, "FBI DCI\n": 1, "Vietnam\n": 1, "Ambassador Lodge\n": 1, "Mr. Bundy Mission\n": 1, "Country Team\n": 1, "American Bundy\n": 1, "Mr. Sullivan\n": 1, "Harriman\n": 1, "McCone\n": 1, "Bundy Mr.\n": 1, "Moyrs\n": 1, "Department Justice\n": 1, "Johnson Washington Post\n": 1, "Mr. Al Friendly\n": 1, "RECORD South Vietnam Situation\n": 1, "Messre\n": 1, "McNamara Ball\n": 1, "Bundy McCone Ambassador Lodge\n": 1, "Ambassador Lodge Lodge\n": 1, "South Vietnamese\n": 1, "Lodge North Vietnam\n": 1, "Saigon Papal\n": 1, "Pope\n": 1, "Papal Delegate\n": 1, "Bishop\n": 1, "Saigon Diem\n": 1, "Lodge Pope\n": 1, "Bishop Thuc\n": 1, "Can\n": 1, "Diem Catholic\n": 1, "Can Lodge\n": 1, "Diem Nhu\n": 1, "Bishop Thuc Saigon\n": 1, "Papal\n": 1, "Papal Ambassador Lodge\n": 1, "SEP\n": 1, "McCone Viet\n": 1, "Viet Cong\n": 1, "Viet Cong Diem\n": 1, "Congress\n": 1, "Vietnam Diem\n": 1, "Vietnam American\n": 1, "Mr. Bundy Truehart\n": 1, "Country Team Ambassador\n": 1, "Ambassador McNamara\n": 1, "South Vietnamese Asian\n": 1, "Johnson Kennedy\n": 1, "Johnson South Vietnam\n": 1, "Bundy Honolulu\n": 1, "Kennedy JAM\n": 1, "Lodge McNamara\n": 1, "Rusk South Vietnam\n": 1, "TOP\n": 1, "DINAR Jy\n": 1, "TATT_\n": 1, "Comte\n": 1, "fViet Vie\n": 1, "Asipow\n": 1, "Pom Ap\n": 1, "L One\n": 1, "Viet Cong Aine Healey\n": 1, "Saigon Diem Con Gout\n": 1, "Cote Cong\n": 1, "Len Pe Ue\n": 1, "Mev Tepafik\n": 1, "Gok\n": 1, "LLLLOLULILULOLLOLUNLLLLLOLM\n": 1, "O\n": 1, "CENTRAL\n": 1, "Buddhist\n": 1, "Diem Buddhist\n": 1, "TOP SECRET\n": 1, "DINAR\n": 1, "TOP DINAR\n": 1, "THE Briefing\n": 1, "Checklist RECORD Discussion\n": 1, "Johnson Johnson\n": 1, "Soviet ICBM\n": 1, "ICBM\n": 1, "Lunar\n": 1, "Soviet Cuba\n": 1, "Soviet Cuban\n": 1, "Venezuela Ecuador\n": 1, "Kennedy Vane\n": 1, "RECORD Discussion Johnson\n": 1, "Mr. Bundy Agency\n": 1, "Checklist Checklist\n": 1, "Checklist Mexico\n": 1, "Mr. Bundy Eisenhower Johnson\n": 1, "Rusk Mexico City\n": 1, "Mexican\n": 1, "Cuban Embassy\n": 1, "Mexican Lee Oswald\n": 1, "FBI Dallas\n": 1, "Rusk Agency\n": 1, "McCone State Department\n": 1, "Rusk United States Arlington\n": 1, "Department States\n": 1}