{"RELEASE\n": 1, "Sood\n": 1, "Dstt\n": 1, "BARGE\n": 1, "FOL\n": 1, "JOE Brecee\n": 1, "FN\n": 1, "Lat Coad Fear La\n": 1, "Boe BONE\n": 1, "PTE\n": 1, "TATHe\n": 1, "CUASSA\n": 1, "BUNIECESf\n": 1, "MIAME\n": 1, "DATEe\n": 1, "CUAS\n": 1, "CONFIDENTIAL\n": 1, "SUNANSS\n": 1, "GROUP OF\n": 1, "ORLANDO\n": 1, "FOE\n": 1, "MIAMI\n": 1, "GIVEN Wes\n": 1, "EXILES\n": 1, "CUBAN\n": 1, "FeE\n": 1, "MIAMr\n": 1, "OTVEN\n": 1, "UNKNOWN\n": 1, "THREE\n": 1, "LEFT\n": 1, "JOHN F. KENNEDY\n": 1, "BOMB\n": 1, "HOUSE\n": 1, "FEY\n": 1, "NEW\n": 1, "CLASS\n": 1, "SOR\n": 1, "ENipede\n": 1, "FAT Prt Noy\n": 1, "MASS\n": 1, "Qittts\n": 1, "CEASSIERCATIONy Bowe Hinn\n": 1, "WEE\n": 1, "SPM Sins\n": 1, "Ded Oe Ti\n": 1, "Cth Ameems\n": 1, "Cuan\n": 1, "Rees\n": 1, "CONFIDENTIAL ALSO\n": 1, "FBI\n": 1, "MIAME CONFIDENTIAL\n": 1, "AKA\n": 1, "NOt\n": 1, "NONE\n": 1, "MIAMI XCERPI\n": 1, "COPY\n": 1, "GIVEN\n": 1, "UNKNOWN EXPLOSION\n": 1, "FBI MIAME\n": 1, "NAY\n": 1, "DISPATCH\n": 1, "Mtetian\n": 1, "Pores City L\n": 1, "Grigte\n": 1, "Ge\n": 1, "Dencas City\n": 1, "Paregrege Bee\n": 1, "Persgreph City\n": 1, "Sovisiente\n": 1, "RaTE\n": 1, "Favtssea\n": 1, "Beeiaptere Cosel\n": 1, "Mens\n": 1, "JECT\n": 1, "Soom\n": 1, "Recuperecian Fee\n": 1, "Bovessat\n": 1, "Cotes\n": 1, "Florid\n": 1, "Grisade BRUCE Avila\n": 1, "Qlensry\n": 1, "Company\n": 1, "Panama\n": 1, "Caty\n": 1, "Aseeeteted\n": 1, "Biaal\n": 1, "OanSa0\n": 1, "FRPLIG\n": 1, "VIATROPICAL\n": 1, "Lo\n": 1, "BISCAYNE\n": 1, "VITAL\n": 1, "SABOTAGES\n": 1, "AED\n": 1, "LOSSES\n": 1, "CORSI\n": 1, "Rs TOYBe\n": 1, "SPECT Re\n": 1, "COORDINATING Cenicee\n": 1, "onTt\n": 1, "Edwin\n": 1, "DISPATCH Foeae ON\n": 1, "EU\n": 1, "Bacte Telegraph\n": 1, "Cubea\n": 1, "General Delegate\n": 1, "OF\n": 1, "LOS\n": 1, "TZ\n": 1, "S0BCE\n": 1, "Panaed\n": 1, "Florida\n": 1, "Unarv\n": 1, "Gsve OF\n": 1, "oF\n": 1, "LNERGO\n": 1, "Pensa\n": 1, "Gvieade BOsC\n": 1, "Aviles\n": 1, "Berens\n": 1, "JUCCBRA\n": 1, "BOSCH\n": 1, "Foqu\n": 1, "FIC\n": 1, "Min STRIECT\n": 1, "VEY\n": 1, "wLAHE\n": 1, "MERK\n": 1, "NONE AMA\n": 1, "FRY\n": 1, "LA\n": 1, "CONFIDENTIAL ORLANDO\n": 1, "FBI MIAMI\n": 1, "CONFIDENTIAL AKA\n": 1, "ERNE Le Pak\n": 1, "CONFIDLNTIAL\n": 1, "AKA FBI\n": 1, "MIAMI EEL\n": 1, "PATE\n": 1, "TAME\n": 1, "FBI FE Division\n": 1, "STGBICRplene Re\n": 1, "Export Aeunce\n": 1, "Tee\n": 1, "FORK Ecaceu\n": 1, "GOS Aast\n": 1, "BOSCH Rabere\n": 1, "Cudee\n": 1, "Peticos\n": 1, "Cals\n": 1, "Sontiag\n": 1, "Nensen\n": 1, "Cubes United Neticons\n": 1, "BOSCH Deebieg\n": 1, "Ge BUSCH\n": 1, "Bitbina\n": 1, "Fopert\n": 1, "DF\n": 1, "Crisn\u00e9n MOECH Aviles\n": 1, "MIRR\n": 1, "Sebot\n": 1, "Statics\n": 1, "Up\n": 1, "ESTE\n": 1, "DATE\n": 1, "SECRET\n": 1, "ORLANDO FBI\n": 1, "MIAMI CROSS\n": 1, "DOCUMENT\n": 1, "MIRR FBI\n": 1, "curSPs\n": 1, "Satna Tela\n": 1, "Ree\n": 1, "D.C.\n": 1, "GYVEN\n": 1, "MIAMI CONFIDENTIA\n": 1, "SUBJECT\n": 1, "FRANK\n": 1, "ORTANDO\n": 1, "CONFIDENTIAL MOVIEMENTO\n": 1, "FBI Patt Fh\n": 1, "ABLE\n": 1, "Lee DiasGis EL\n": 1, "MIAMI MIRR\n": 1, "JAF\n": 1, "Le\n": 1, "PERSONS\n": 1, "WZ\n": 1, "LLISTRCT\n": 1, "Z0lsTabscaT\n": 1, "SECRET SSS\n": 1, "CHA\n": 1, "ARMS\n": 1, "CONTROL\n": 1, "CONSPIRACY\n": 1, "NEUTRALITY\n": 1, "MIAME FRE\n": 1, "F Secon\n": 1, "SANTA\n": 1, "CUBA\n": 1, "LOUIS\n": 1, "BERTOY\n": 1, "MIAME JOSE\n": 1, "OAs\n": 1, "SANTIAGO DE\n": 1, "MIAME JOSE DIAZ\n": 1, "cuBA\n": 1, "Lorne\n": 1, "MIAMI W\n": 1, "MIAMI Ope BARBARO BALAN\n": 1, "Morr\n": 1, "msraoouerOn\n": 1, "WnBVING\n": 1, "AVENUE\n": 1, "MIAMI OQ O\n": 1, "Corr\n": 1, "CITE\n": 1, "Gan Coll\n": 1, "Gmmeonee GO\n": 1, "ARTHUR\n": 1, "DEFENDANT\n": 1, "MIAMI POSSIBLY\n": 1, "PLEASE\n": 1, "FORWARD\n": 1, "ALREADY\n": 1, "COMMENTS\n": 1, "OPERATIONS\n": 1, "SECURITY\n": 1, "NABFERRER\n": 1, "MNOWENG\n": 1, "KIND\n": 1, "EVER\n": 1, "EMPLOYED\n": 1, "AGAINST\n": 1, "INCLUDING\n": 1, "SCSWIRL\n": 1, "THOMAS Jy\n": 1, "FLORES\n": 1, "PROHIBITED\n": 1, "FLY\n": 1, "Cass\n": 1, "SECRET SSO\n": 1, "RAZ\n": 1, "Helen\n": 1, "WOPa\n": 1, "DIRECTOR C1At\n": 1, "THE\n": 1, "ARMY\n": 1, "TO\n": 1, "THE AIR\n": 1, "WHITE\n": 1, "FBI PGeents Ganev\n": 1, "MOVINIENTO\n": 1, "INTERNAL\n": 1, "SECURITY BOS\n": 1, "Was\n": 1, "SOVERNMENT\n": 1, "INTELLIGE\n": 1, "SIXTYSEVEN\n": 1, "Ae\n": 1, "TELEPHONE\n": 1, "FAST\n": 1, "MARCH\n": 1, "AMERICAN\n": 1, "Pt LOT\n": 1, "INTENDED Njby\n": 1, "AND\n": 1, "SECRET Tee\n": 1, "Teteltluo\n": 1, "TabGed\n": 1, "SIsTVseves\n": 1, "PuslO\n": 1, "aLickO\n": 1, "Cura\n": 1, "TUDE\n": 1, "THE FLIGHT\n": 1, "vOULD\n": 1, "PILOT\n": 1, "BETVLES\n": 1, "THOUSAND\n": 1, "GLCORD\n": 1, "WHO\n": 1, "ASSOCIATED\n": 1, "BOSCH THE\n": 1, "WAS\n": 1, "OW\n": 1, "SERTYSEVED\n": 1, "THE SIXTYSEVEN\n": 1, "BIXTYs\n": 1, "BOSCH AMERICAN\n": 1, "OVER\n": 1, "BOSCH THAT\n": 1, "RAID\n": 1, "RENTED\n": 1, "QIRPLANE\n": 1, "PILOT MISSION\n": 1, "AND HUNDRED\n": 1, "THE TARGET\n": 1, "Coad\n": 1, "SuBAR\n": 1, "NORTH\n": 1, "__THIs\n": 1, "SOURCE\n": 1, "VERY\n": 1, "CREW OF\n": 1, "THE AIRPLANE\n": 1, "THE SOURCE OF\n": 1, "GAD Cb\n": 1, "GORMTARf\n": 1, "LEN\n": 1, "OF Tat Pisme\n": 1, "VOLS Yast\n": 1, "BOSCH VOULD\n": 1, "TvO\n": 1, "SUATYSEVES\n": 1, "BEILF\n": 1, "VIBMIZE\n": 1, "BOSCH OF Tue\n": 1, "FLORIDA\n": 1, "I8\n": 1, "PEING\n": 1, "VOULD\n": 1, "CRRANGLENLUTS\n": 1, "AUD\n": 1, "NEN\n": 1, "COkaneal\n": 1, "Wesess\n": 1, "EEE\n": 1, "BOSH\n": 1, "ORLARCO\n": 1, "Ula\n": 1, "WITH\n": 1, "FORM OF\n": 1, "GECRET\n": 1, "EMIGAE\n": 1, "VALL\n": 1, "Cabs O45\n": 1, "Oe\n": 1, "Ot OE\n": 1, "Stetion\n": 1, "sxAye\n": 1, "PECs\n": 1, "anlT Spe\n": 1, "Compan\n": 1, "Gatien Gated\n": 1, "Cuban Association\n": 1, "ANC\n": 1, "HirreComandes Aa\n": 1, "Yoru\n": 1, "Avila Felipe\n": 1, "RIVERO\n": 1, "Dias\n": 1, "ANC United Btates\n": 1, "CLA\n": 1, "Philip G.\n": 1, "ELMARD Attacheant\n": 1, "NOT\n": 1, "DATE HEADQUARTE\n": 1, "OnTE\n": 1, "Toke\n": 1, "Le AMOT Report\n": 1, "WANT\n": 1, "OES\n": 1, "RULER\n": 1, "NONE StCRET Po\n": 1, "Rip Copy\n": 1, "Bele\n": 1, "Classes Ceres\n": 1, "SCER\n": 1, "CITE PRIG\n": 1, "TYPIC Gu\n": 1, "LOCAL\n": 1, "PERSOM\n": 1, "ORLANDO WHO\n": 1, "CENTRAL\n": 1, "REFUSED\n": 1, "SUTIERREZ\n": 1, "RAUL\n": 1, "JNWAVE\n": 1, "Saba TALKED\n": 1, "GUTIERREZ\n": 1, "TWO\n": 1, "SHE\n": 1, "DARK\n": 1, "THIN\n": 1, "sEcoup\n": 1, "AIRCRAFT\n": 1, "ATTACK\n": 1, "MATANZAS\n": 1, "Los\n": 1, "VILLAS\n": 1, "TARGETS Bur\n": 1, "NO\n": 1, "SECRET ADVISED\n": 1, "AAT\n": 1, "CFMU\n": 1, "CUD\n": 1, "GMASHET\n": 1, "STAT10\n": 1, "EVELIO\n": 1, "HAVANA\n": 1, "FORCE\n": 1, "HO\n": 1, "MIAMI SECRET\n": 1, "dA Nop\n": 1, "Cc Bs\n": 1, "SECRET CITE\n": 1, "OCTO3ER\n": 1, "GIVEN WHEN\n": 1, "COMPANIONS\n": 1, "OCTOSER\n": 1, "TERREZ\n": 1, "CHIEF OF\n": 1, "BEEN\n": 1, "TELEP\n": 1, "JORGE\n": 1, "ATTEND\n": 1, "TO L\n": 1, "ALSO\n": 1, "ORN\n": 1, "DEFENSE\n": 1, "TRY\n": 1, "DOMINATION\n": 1, "HOMELAND\n": 1, "COMNUNIST\n": 1, "WHICH\n": 1, "OF BASE\n": 1, "GONDUCTING\n": 1, "SANE\n": 1, "THE GARBLE FOR\n": 1, "GORDON\n": 1, "GORDO\n": 1, "SITE FOR\n": 1, "NAPLES\n": 1, "WHICH Sesh\n": 1, "QUIN\n": 1, "USE\n": 1, "OCTCSER\n": 1, "CUED\n": 1, "LOCATED\n": 1, "HOVEVER\n": 1, "RISER Has Pag\n": 1, "oFs\n": 1, "YAS\n": 1, "POSTPONTD\n": 1, "STCAUSE OF\n": 1, "HURRICANE\n": 1, "SCHEDULED\n": 1, "KC\n": 1, "WILL\n": 1, "HOS\n": 1, "SITE\n": 1, "CUSTODIANS\n": 1, "FOR\n": 1, "HELD\n": 1, "MIRR AP\n": 1, "Mwt HERALD\n": 1, "ACTIVITIES OF\n": 1, "DATE THEY\n": 1, "SITE TO\n": 1, "OFFICIALS\n": 1, "CONTACTEL\n": 1, "RIGSER\n": 1, "ALERTED\n": 1, "MORNING6\n": 1, "Qy RIGGEI NO\n": 1, "TARP\n": 1, "BE\n": 1, "NAPLES ALREADY\n": 1, "WERE\n": 1, "VESA\n": 1, "OCTOSER NOT\n": 1, "MENTION\n": 1, "MIAMI HERALD\n": 1, "MIAMI NAPLES\n": 1, "COVERAGE OF\n": 1, "SECnef\n": 1, "NOT VOFA\n": 1, "AT\n": 1, "GUTICRREZ\n": 1, "Len\n": 1, "ORGS\n": 1, "TRY INTIMIDATE\n": 1, "Fathin\n": 1, "Nae\n": 1, "Meese\n": 1, "ADEA\n": 1, "PIR\n": 1, "Tao\n": 1, "SITES\n": 1, "HAVING\n": 1, "WAS VIGILANCE\n": 1, "DATE MIRR\n": 1, "NOTA3LY\n": 1, "ACTIVITIES\n": 1, "AND INDICATES\n": 1, "RIVERO ATTITUDE OF U.S\n": 1, "GOVT\n": 1, "U.S.\n": 1, "BASE FOR\n": 1, "FURTHER\n": 1, "MIRR COMPARED Ri\n": 1, "PAGE\n": 1, "SECRET Oo\n": 1, "Sar Tat\n": 1, "ASI\n": 1, "ESET\n": 1, "GOsyne\n": 1, "UENRIE\n": 1, "FT\n": 1, "JUVAVE\n": 1, "IDSD\n": 1, "AMSEC\n": 1, "SENSITIVE\n": 1, "DATA\n": 1, "COMBINED\n": 1, "SECRET Ree REN Segment\n": 1, "ULITS\n": 1, "GIVEN MIRR\n": 1, "FBI MEANT\n": 1, "MIAMI NONE\n": 1, "FSI\n": 1, "MIRR oY\n": 1, "DISPATCH Beatera Renispbore P55\n": 1, "Station\n": 1, "Ge InwavE\n": 1, "Owere Clone\n": 1, "Aailva Mace\n": 1, "Orlando Required\n": 1, "Nore\n": 1, "JBEAVE\n": 1, "Fes BOSCH\n": 1, "FSS St\n": 1, "AMOT\n": 1, "Diario\n": 1, "Lae Ausricas\n": 1, "BOSCH CIA\n": 1, "Cuba\n": 1, "AMOT PRILIP\n": 1, "Blatervutien\n": 1, "Heroes\n": 1, "ELMARD\n": 1, "SECRET HINN\n": 1, "Cuba Opiande\n": 1, "Orlando\n": 1, "Sepa\n": 1, "Laltea\n": 1, "Yivedca\n": 1, "United\n": 1, "CG\n": 1, "CLA OL\n": 1, "Pherfo Las Americas SOvacks\n": 1, "MIRR Au3t\n": 1, "Sy\n": 1, "Alok Vi\n": 1, "ORLANDO Yorse\n": 1, "Joamea\n": 1, "Dis\n": 1, "UAB Atotd\n": 1, "Cala\n": 1, "Mareos Rodricuos\n": 1, "Jos\u00e9 Diaz\n": 1, "Gerulie Guti\u00e9rrez\n": 1, "soSume\n": 1, "Basch\n": 1, "Fay Rembres\n": 1, "Lasiacs\n": 1, "Wolay\n": 1, "Swaaner\n": 1, "SLA\n": 1, "Coatrai\n": 1, "Misligenne\n": 1, "eR\n": 1, "OBE\n": 1, "Grlendo Beeshcrstacl\n": 1, "ARNO\n": 1, "sBEa\n": 1, "Osegenee _. GH Bere F008\n": 1, "Ee\n": 1, "REARS\n": 1, "BEKALF OF\n": 1, "NN Re\n": 1, "OALANOO\n": 1, "Ewe\n": 1, "SECRET legCassin\n": 1, "Avance\n": 1, "RIJAN\n": 1, "SUAREZ\n": 1, "OOIs\n": 1, "SERGIO\n": 1, "SANCHEZ\n": 1, "BOSCH IDs\n": 1, "REPORT\n": 1, "Sueus\n": 1, "REPAIR OF\n": 1, "USED\n": 1, "THE MIRR\n": 1, "INFILTRATE\n": 1, "INTO\n": 1, "VILTAS\n": 1, "UNITED\n": 1, "STATES\n": 1, "Mua C29\n": 1, "Lana\n": 1, "Soaks\n": 1, "INTEL\n": 1, "BLAS\n": 1, "GUPDATAS\n": 1, "AWD\n": 1, "ORR\n": 1, "DATE CAMTAUP\n": 1, "UAISON\n": 1, "bE\n": 1, "Copy\n": 1, "Oe Wd\n": 1, "BBkgr\n": 1, "THE GROUP\n": 1, "TECHINQUES OF\n": 1, "REPORTS\n": 1, "USD\n": 1, "Ttactiy\n": 1, "FER Lb\n": 1, "Fete\n": 1, "Reefton\n": 1, "BATE\n": 1, "DISTRIBUTED\n": 1, "GLAREIFICAT\n": 1, "Alb\n": 1, "DUCTION\n": 1, "CLO\n": 1, "DELO\n": 1, "CATER\n": 1, "CAR\n": 1, "CON\n": 1, "CONFIDENTIAL INFILTRATE\n": 1, "INTO VILTAS\n": 1, "UNITED STATES\n": 1, "MIAMI REPAIR\n": 1, "MIRA\n": 1, "MAR\n": 1, "INFORMATION\n": 1, "THE GROUP Sees\n": 1, "SERGIO SANCHEZ\n": 1, "FELD\n": 1, "APPRAISAL\n": 1, "EMIGRES\n": 1, "TECHNIQUES OF\n": 1, "MIAMI FLORIDA\n": 1, "WAS VESSEL\n": 1, "THE MOVIMIENTO\n": 1, "MIRR INSURRECTIONAL\n": 1, "SUAREZ COMPLETED\n": 1, "THE THE\n": 1, "MIRR VESSEL\n": 1, "INFILTRATE NORTH\n": 1, "THE GROUP GNLY\n": 1, "THE WEATHER\n": 1, "TRIP\n": 1, "Natioal Detoee\n": 1, "Uniod Sats\n": 1, "Bacgcltte\n": 1, "QTATEINA\n": 1, "NAVY\n": 1, "Uaracuan\n": 1, "WESSEL\n": 1, "FOC\n": 1, "Lee\n": 1, "oF SHALLER\n": 1, "ORLANDO LEADER OF\n": 1, "HAD\n": 1, "Trt\n": 1, "FIELD\n": 1, "CINCSO\n": 1, "CINCLANT\n": 1, "COMmWE\n": 1, "MIAMI SYAYC\n": 1, "FO\n": 1, "CUSTOMS\n": 1, "Beait SE\n": 1, "CONFIDENTIAL BORDER\n": 1, "AND BURSECT\n": 1, "MIRR MIAME\n": 1, "QTVEN\n": 1, "BURIECT\n": 1, "CIMRAN\n": 1, "RECE\n": 1, "FRE\n": 1, "MIAME ENN\n": 1, "GIRw\n": 1, "Chessreee Deol\n": 1, "Sat O\n": 1, "REPO\n": 1, "SECRET aMoy\n": 1, "FYE\n": 1, "TELEPHONE RFFO\n": 1, "DTD\n": 1, "MOV\n": 1, "CATED\n": 1, "GAPCIA\n": 1, "WHO BOND\n": 1, "ORIGINALLY\n": 1, "NOV\n": 1, "TELEPHONE HARTFORD\n": 1, "UNIVERSITY\n": 1, "REDUCED\n": 1, "aT\n": 1, "UNIVERSITY FOR\n": 1, "ASKED\n": 1, "PUBLIC\n": 1, "BUT\n": 1, "PUBLIC SAME\n": 1, "CAVEAT\n": 1, "BOSCH HARTFORD\n": 1, "HAVE\n": 1, "UNIVERSITY ATTEMPT\n": 1, "BOSCH WSawES Le\n": 1, "HENCEFORTH\n": 1, "INDICATED\n": 1, "PREVIOUSLY\n": 1, "Nia PLANED\n": 1, "ERructine\n": 1, "PINAR\n": 1, "SECRET WAVE\n": 1, "PEL\n": 1, "SEE\n": 1, "FOR Stamey\n": 1, "FOR Informal\n": 1, "Ese\n": 1, "RIO\n": 1, "HOT\n": 1, "INTEND\n": 1, "UNIVERSITY NOT FOR Ant\n": 1, "GARCIA\n": 1, "FYI\n": 1, "DID\n": 1, "NOV ORLANDO\n": 1, "HARTFORD\n": 1, "HARTFOPD\n": 1, "SECRET IRR\n": 1, "WOULD\n": 1, "APPRECIATE\n": 1, "VERSITY\n": 1, "STUDENTS\n": 1, "WHETHER\n": 1, "AND ESTIMATE\n": 1, "ASSUME\n": 1, "ODENVY\n": 1, "CONTINUE\n": 1, "VAVE\n": 1, "INTEND DISSEMINATE\n": 1, "LOCALLY\n": 1, "OY Chesssee\n": 1, "O0ante\n": 1, "SECRET OEPOCEL\n": 1, "PROn\n": 1, "COPE Copy\n": 1, "DIR\n": 1, "FOR INFORMATION\n": 1, "AHOT\n": 1, "BARRERA\n": 1, "DIAZ\n": 1, "oF COMMITTED\n": 1, "OBYOKE\n": 1, "SECRET AnOT\n": 1, "NOV BARRERA\n": 1, "Diaz\n": 1, "AND NEW\n": 1, "PEDRO\n": 1, "YANES OF\n": 1, "MIRR WHICH\n": 1, "COMPLAIN\n": 1, "INSULTS\n": 1, "NEW Pott Ett\n": 1, "Cor\n": 1, "PL\n": 1, "OF Mle FUG\n": 1, "ORE\n": 1, "BOSSE\n": 1, "Cars\n": 1, "PERACICN\n": 1, "REAT\n": 1, "Te\n": 1, "CRLANOG\n": 1, "BOSSIBLE\n": 1, "ALINCHE\n": 1, "Reuatt\n": 1, "Gate\n": 1, "Gvmceteen\n": 1, "DOCUMENT BgNseT\n": 1, "ORIONSAE\n": 1, "DOCUMENT OF\n": 1, "C8OSS\n": 1, "OCn\n": 1, "Os\n": 1, "Gewate Cave\n": 1, "BATE OF\n": 1, "GoeLeeteen\n": 1, "Cttsiwreatee\n": 1, "PIALINEAI\n": 1, "SEX\n": 1, "ORLANDO PLANNING\n": 1, "AERIAL\n": 1, "AVILA\n": 1, "Inna Beant ER\n": 1, "REHAB\n": 1, "FILE\n": 1, "BUSCH\n": 1, "Nou\n": 1, "Ges\n": 1, "SPR\n": 1, "QALANOO\n": 1, "LEADER\n": 1, "MIRAs\n": 1, "RECOVERY\n": 1, "SHE AUOLFO\n": 1, "HAS\n": 1, "PARTICIPATE\n": 1, "THE OPERATION\n": 1, "GOL\n": 1, "NOV URE\n": 1, "ORLANDO Par\n": 1, "COSLIMLAL\n": 1, "Orwentin\n": 1, "SSRN\n": 1, "Sawer\n": 1, "POCmET Tesesste\n": 1, "ShCaat100\n": 1, "COCMERT\n": 1, "CHOSE\n": 1, "OF Gemectn\n": 1, "SEBah Hatta\n": 1, "rerrrT\n": 1, "OF Ox\n": 1, "AVILA SUSCR Bl\n": 1, "UUs\n": 1, "URLANDO\n": 1, "GUN\n": 1, "INSURKECTIONAL\n": 1, "SUN\n": 1, "EMIGRES Tu\n": 1, "FUREIGN\n": 1, "SA\n": 1, "t60ED\n": 1, "WIR\n": 1, "SECRET Din INFO\n": 1, "CITE TED Pe\n": 1, "URCHURST\n": 1, "MHMOOSE\n": 1, "ODFOAM\n": 1, "JUAM\n": 1, "BARRERA DIAZ\n": 1, "ASSOCIATED BOSCH\n": 1, "AVILA HEAD\n": 1, "MILITANT\n": 1, "ODFOAM CLEARED\n": 1, "ODFOAM OPINION\n": 1, "SUBJECTS\n": 1, "BOSCH ASSOCIATION\n": 1, "NEGRO\n": 1, "BECAUSE\n": 1, "ROLLASON\n": 1, "DELEGATE\n": 1, "MEXICO FOR\n": 1, "AGENCIA DE\n": 1, "Aste\n": 1, "DE\n": 1, "coRC\n": 1, "MEXICO\n": 1, "SECOET\n": 1, "ROREBZA Diaz\n": 1, "CAS\n": 1, "HEERO\n": 1, "FEEICO\n": 1, "Parete\n": 1, "Rio\n": 1, "coNnr\u00e9\n": 1, "Rete\n": 1, "CRA\n": 1, "oeSSR Mee\n": 1, "ION\n": 1, "RIMS\n": 1, "MIANT\n": 1, "MINING OF\n": 1, "SAN\n": 1, "FAT\n": 1, "MIAMI Le LE\n": 1}