{"RELEASE\n": 1, "JOHN F. KENNEDY\n": 1, "A682\n": 1, "JMWAVE\n": 1, "WHIsA\n": 1, "Ale\n": 1, "DPF\n": 1, "LOG\n": 1, "TYPIC\n": 1, "DEFERRED\n": 1, "CITE\n": 1, "FOR\n": 1, "FEARS\n": 1, "OF\n": 1, "JAN\n": 1, "JAN WIRE\n": 1, "JAN CASTRO\n": 1, "CITED\n": 1, "SAID\n": 1, "MENOYO\n": 1, "ALMOST\n": 1, "AND\n": 1, "CUBAN\n": 1, "LIKELY\n": 1, "AND COULD\n": 1, "PART OF\n": 1, "MAN\n": 1, "ORDERS\n": 1, "GUTIERREZ\n": 1, "WISH\n": 1, "ROWS\n": 1, "ASS\n": 1, "CREWMEN\n": 1, "SINCE\n": 1, "FERIOD\n": 1, "REPRODUCTION\n": 1, "THE\n": 1, "ISSUING\n": 1, "Copy Ma\n": 1, "TW\n": 1, "MET\n": 1, "UFGA\n": 1, "NOT\n": 1, "OAT\n": 1, "PRR\n": 1, "Fee PRETTY\n": 1, "Bate\n": 1, "PARI\n": 1, "AAD\n": 1, "SiS\n": 1, "SECRET\n": 1, "NO\n": 1, "FILE\n": 1, "VOITICU\n": 1, "DATE\n": 1, "SEG\n": 1, "DEFERRED CONF\n": 1, "NO CO\n": 1, "SECRET SUCGEST\n": 1, "VIEW\n": 1, "INFO\n": 1, "NOT TRY\n": 1, "LOCATE\n": 1, "GPIDEAL\n": 1, "RETURN\n": 1, "FEB\n": 1, "CITED SERVICES\n": 1, "TRY\n": 1, "LOCATE MARIO\n": 1, "GIL\n": 1, "PEDRO\n": 1, "VAZQUEZ\n": 1, "TWO OF\n": 1, "ALL\n": 1, "GLORia\n": 1, "CABRERA\n": 1, "HAVANA\n": 1, "ALSO\n": 1, "GLORIA\n": 1, "AS\n": 1, "Pe OTUE\n": 1, "COORDINAT\n": 1, "SEGRET\n": 1, "INE\n": 1, "ISSUING Cind\n": 1, "Brat\n": 1, "COMES\n": 1, "MTD\n": 1, "SINCE GLORIA\n": 1, "THREE\n": 1, "Poe\n": 1, "BATE\n": 1, "MARINO\n": 1, "OR\n": 1, "FEBLES\n": 1, "OWNER OF\n": 1, "Ao10\n": 1, "Cane\n": 1, "SINCE PLS\n": 1, "HMM\n": 1, "LOCATE PRESENCE\n": 1, "ME\n": 1}