{"RELEASE\n": 1, "JOHN F. KENNEDY\n": 1, "HOUSE\n": 1, "WELT\n": 1, "ASSASSINATIONS\n": 1, "AFF\n": 1, "B33Y79\n": 1, "INCLUSI\n": 1, "UNI\n": 1, "DATE\n": 1, "PRINT\n": 1, "SIGNATURE OF\n": 1, "REVIEWING\n": 1, "NO\n": 1, "COPIED\n": 1, "THIS\n": 1, "haFeisatter\n": 1, "Fela\n": 1, "United\n": 1, "CPL\n": 1, "WIINpss\n": 1, "Corn\n": 1, "Lila\n": 1, "Pel L\n": 1, "REPORT\n": 1, "CONTACT\n": 1, "WIROGUE\n": 1, "WIROGUE HARVARD\n": 1, "HARVARD\n": 1, "Dave\n": 1, "Dave Volta\n": 1, "Kuhwaldstr\n": 1, "WIROGUE _Bochler Company\n": 1, "Davett\n": 1, "Murmann\n": 1, "Subject\n": 1, "Germany\n": 1, "WIROGUE AIS\n": 1, "WIROGUE Agency\n": 1, "Subject Paris\n": 1, "Erench\n": 1, "Freneh\n": 1, "British\n": 1, "WIROGUE French\n": 1, "WIROGUE French French Intelligence\n": 1, "Service\n": 1, "Donte\n": 1, "WIROGUE French Paris\n": 1, "Fretich\n": 1, "WIROGUE Jook\n": 1, "Subject WIROGUE\n": 1, "Murmann Mr.\u00b0\n": 1, "Murmann WIROGUE\n": 1, "kRaxxhe\n": 1, "Subject West\n": 1, "German\n": 1, "Subject Subject\n": 1, "WIROGUE WIROGUE\n": 1, "-and\u00b0C\n": 1, "Germa West\n": 1, "WcT\n": 1, "Acres\n": 1, "WIROGUE Kaiserstr\n": 1, "Taunus\n": 1, "Anlage\n": 1, "GIN\n": 1, "ORME\n": 1, "Subject Frankfurt\n": 1, "Munich\n": 1, "Munich Would\n": 1, "Munich Subject\n": 1, "U.S.\n": 1, "Subject Subject Subject\n": 1, "DM\n": 1, "French\n": 1, "Subject Rel\n": 1, "DARONNAT_\n": 1, "Munich European\n": 1, "Subject Munich\n": 1, "Subject Munich Frankfurt\n": 1, "Munich Subject SSN\n": 1, "Subject Munich Munich\n": 1, "Frankfurt\n": 1, "Nagely\n": 1, "Subject Munich Nagely\n": 1, "Frankfurt CRE\n": 1, "WBWORANDD FOR\n": 1, "THE\n": 1, "RECORD\n": 1, "Schmid PP\n": 1, "Clarence\n": 1, "Clar\u00e9ne\u00e9e\n": 1, "Cond\n": 1, "HARVARD Subject\n": 1, "Subject OCA\n": 1, "Bonn\n": 1, "Subject HARVARD\n": 1, "oO\n": 1, "OCA\n": 1, "Subject HARVarnbD\n": 1, "Subject BFV\n": 1, "Subject Germany\n": 1, "HARVARD Bonn\n": 1, "Subject OCA Subject\n": 1, "BEV\n": 1, "Coleg\n": 1, "Subject OCA BFV\n": 1, "OPES\n": 1, "TY\n": 1, "BAM\n": 1, "TaN\n": 1, "NAL\n": 1, "BFV\n": 1, "Ovided\n": 1, "HARVARD Lebenslauf\n": 1, "PEPURT\n": 1, "OR Be\n": 1, "Glauburgstr\n": 1, "ORME Subject\n": 1, "January\n": 1, "Slip\n": 1, "Simple\n": 1, "Subj\u00e9ct\n": 1, "Subject C\n": 1, "Konto\n": 1, "Loew\n": 1, "Munich Munich\n": 1, "Munich Subject Subject\n": 1, "CECNEY\n": 1, "See\n": 1, "REPORT Suaigct\n": 1, "WIROGUE Hohem\n": 1, "Munich Subject Subject Subject\n": 1, "LTS\n": 1, "Subject Subject buSiness\n": 1, "Subject SSE\n": 1, "U.S. Canada\n": 1, "Australia\n": 1, "INTERPOL\n": 1, "Russia\n": 1, "Soviet\n": 1, "Subject HARVARD Was\n": 1, "Army\n": 1, "Wevcan\n": 1, "HARVARD OOP\n": 1, "CONTACT WITH\n": 1, "Cc\n": 1, "Subject English\n": 1, "Subject English Lebenslauf\n": 1, "German Subject\n": 1, "Tunch\n": 1, "German Subject Subject\n": 1, "N00\n": 1, "Aeriananai\n": 1, "Le\n": 1, "Sy\n": 1, "TSSpaaS\n": 1, "MEMORANDU FOR\n": 1, "THE RECORD\n": 1, "MiRoceE\n": 1, "SON\n": 1, "Advisor\n": 1, "Rame\n": 1, "Subject Simon Sand\u00e9rs\n": 1, "Frank Simon\n": 1, "Sanders\n": 1, "John\n": 1, "Frank Simon Sanders\n": 1, "John Reiseausweis Sorgen\n": 1, "Subject Subject Antrag\n": 1, "John Subject\n": 1, "Sam\n": 1, "Sam Lohnsteurkarte\n": 1, "Subject Subject BFV\n": 1, "Subject OT\n": 1, "Ate\n": 1, "Speciat\n": 1, "John eTeRny\n": 1, "Jae\n": 1, "MI Group\n": 1, "Bonn Wilms\n": 1, "aTE\n": 1, "John Bona\n": 1, "Besser\n": 1, "Kuhwaldstr Lebens\n": 1, "Soviet Subject\n": 1, "Subject Subject Cc\n": 1, "Subject Octobe Cc\n": 1, "U.S. Army\n": 1, "Subject ARToee\n": 1, "Subject Wis\n": 1, "Starlettograph\n": 1, "Subjec\n": 1, "Leo\n": 1, "Hanov\u00e9r Fair\n": 1, "Subject cuGuba\n": 1, "FAT\n": 1, "Sabjee __\n": 1, "BAT\n": 1, "Hotel\n": 1, "Soe\n": 1, "Subject Lgbenslauf\n": 1, "German Subject DM-1,000\n": 1, "Subject Subject POwt\n": 1, "Subject Geericalg\n": 1, "Subject DARONNAT\n": 1, "Suggestion\n": 1, "Comey\n": 1, "Resettlement Gfe\n": 1, "Vocation\n": 1, "Korleas Da Adu Fomen\n": 1, "TULpwong\n": 1, "Glee\n": 1, "COT Aba\n": 1, "Johnson\n": 1, "BKZ\n": 1, "Subject Any\n": 1, "SNSe\n": 1, "Newed Deethtter\n": 1, "PANSETSESS\n": 1, "ERT\n": 1, "EPShien\n": 1, "infA\n": 1, "Sout\n": 1, "HERAT\n": 1, "TET\n": 1, "Renee\n": 1, "Sa\n": 1, "D600\n": 1, "Baia\n": 1, "Subject Subject Subject Subject\n": 1, "Subject Subject WIROGUE\n": 1, "Crass\n": 1, "CG\n": 1, "Subject SECRET\n": 1, "Ne\n": 1, "Sul\n": 1, "Teel See\n": 1, "Aanuary\n": 1, "Aris\n": 1, "Ope\n": 1, "Subject Subject Subject Subject Gho3\n": 1, "SECRET\n": 1, "Heaton\n": 1, "REPORT WITH\n": 1, "AGENT\n": 1, "Subject Libensiaut\n": 1, "German Subject Said\n": 1, "Subject Wilms\n": 1, "Wilms\n": 1, "BND\n": 1, "Subject Frank\n": 1, "Simon\n": 1, "Subject Tbis\n": 1, "Labenslaut\n": 1, "Georgian\n": 1, "Subject RR Re\n": 1, "Georg\n": 1, "Subject Ss Frank\n": 1, "Btery\n": 1, "Simon Sanders\n": 1, "Subject Georgian\n": 1, "Geir OR DerecTon\n": 1, "wiRocuE\n": 1, "Knows\n": 1, "Soon\n": 1, "Ereitrom\n": 1, "SECRET OIE\n": 1, "Subject St Dae\n": 1, "CRN\n": 1, "Germany Subject\n": 1, "France\n": 1, "Subject Subject Cara\n": 1, "Serer\n": 1, "SSR\n": 1, "Pee Davo\n": 1, "DARONNAT\n": 1, "OF\n": 1, "Subject Subject South America\n": 1, "Subject South\n": 1, "WEROGUE\n": 1, "DATE Kuhwaldstr\n": 1, "ORME DARONNAT\n": 1, "Subject AcENT\n": 1, "DEFECTOR\n": 1, "REPORT Marea\n": 1, "Subject Subject Subject Say\n": 1, "Kuhwaldstr Apartment\n": 1, "Kubwaldstr\n": 1, "SPT\n": 1, "MPEP Wy\n": 1, "Zecscea\n": 1, "Geri\n": 1, "Aceitt\n": 1, "Subject heSe\n": 1, "France Frankfurt\n": 1, "VersSicherungskarte\n": 1, "Labenslauf\n": 1, "Germany Subject Subject\n": 1, "SECRET MATERIAL\n": 1, "RESETTLEMENT\n": 1, "May\n": 1, "HARVARD HARVARD\n": 1, "Subject South Subject\n": 1, "Carip\n": 1, "German German\n": 1, "German Steps\n": 1, "South America\n": 1, "HARVARD ICEM\n": 1, "South\n": 1, "American\n": 1, "HARVARD Wagner\n": 1, "Story\n": 1, "HARVARD Alex\n": 1, "F\u00e9place\n": 1, "ONE\n": 1, "Union\n": 1, "Georgia\n": 1, "Turkey\n": 1, "WIROGUE Subject\n": 1, "Satisfactorily\n": 1, "KUBARK\n": 1, "CXL\n": 1, "DRC\n": 1, "REPGRT\n": 1, "Sat\n": 1, "Cas\u00e9\n": 1, "Subject Soup\n": 1, "WIROGUE Case Officer\n": 1, "Case Officer\n": 1, "Subject HARVARD Alfred Naegele\n": 1, "Glauburgstr Subject\n": 1, "Subject Subject Nacgele\n": 1, "Mf XS\n": 1, "Subject Solved\n": 1, "Subject Subject Herr Nacgele\n": 1, "Case\n": 1, "Nacgele\n": 1, "Subject Subject Herr\n": 1, "Nacgele Subject\n": 1, "SEC\n": 1, "Ure\n": 1, "P PL\n": 1, "Subject Kuhwaldst\n": 1, "Subject Ss\n": 1, "Na\u00e9gele\n": 1, "Taunu\n": 1, "Camp King\n": 1, "Herr Naeg\u00e9le\n": 1, "Camp\n": 1, "Officer\n": 1, "Subject Subje\u00e9t\n": 1, "niOffi\n": 1, "Subject ioWn\n": 1, "Kuhwaldstr Subject\n": 1, "Subject Case Officer\n": 1, "Subje\n": 1, "Subject Case Offic\n": 1, "Case Subject\n": 1, "Subject German\n": 1, "Case Officer South\n": 1, "America\n": 1, "Germany SECRET\n": 1, "Pte Sh\n": 1, "Subject Live\n": 1, "Case Officer Case Officer\n": 1, "Subject Same\n": 1, "Interpol\n": 1, "Subject CHARVARD\n": 1, "Subject SE\n": 1, "mT Se\n": 1, "Officer West\n": 1, "WIROGUE vECTOR\n": 1, "Germany REPORT\n": 1, "WIROUGE\n": 1, "Orne K.\n": 1, "Ofticer\n": 1, "Subject Subject Mr. Sanders\n": 1, "Case Officer Legend\n": 1, "Case Case Officer\n": 1, "Subject REPORT\n": 1, "WiTH_AGERT\n": 1, "Se T\n": 1, "Subject AT\n": 1, "Subject Electric\n": 1, "Rese\n": 1, "Case Officer Comez\n": 1, "Subject Subject Case Offi\n": 1, "Camp demonStrate\n": 1, "BKZ Officer\n": 1, "Subject OR Derecron\n": 1, "Germany South\n": 1, "Subjectti\u00e9\n": 1, "America Subject\n": 1, "BKZ REPORT\n": 1, "CONTACT Marit\n": 1, "Riches Fed Gemmany\n": 1, "Russian\n": 1, "Jong\n": 1, "BKZ Russian\n": 1, "PFosb\u00e9cts\n": 1, "Russian Germany\n": 1, "PPE Sn\n": 1, "Subject Beginnin\n": 1, "Germany CO\n": 1, "Headquarters\n": 1, "Soviet Union\n": 1, "Russian Subject\n": 1, "Subject Russian\n": 1, "Russian Subject Chile\n": 1, "John Wilms\n": 1, "Subject Chile\n": 1, "Chilean\n": 1, "Subject Orme K. Daronnat\n": 1, "Alex\n": 1, "Wurzay\n": 1, "WIROGUE Subject Russian\n": 1, "Buil\n": 1, "Sovie\n": 1, "Chile\n": 1, "Rothifgs\n": 1, "Boob\n": 1, "Lacan Katy\n": 1, "Cleon\n": 1, "Lond\n": 1, "gBaty\n": 1, "ARE\n": 1, "Bowes\n": 1, "Baronnat\n": 1, "Subject Conan\n": 1, "ArSeitsvera\n": 1, "ttYung\n": 1, "Avett\n": 1, "Cabal Oboe\n": 1, "Rn\n": 1, "Wtee\n": 1, "South Jack Re\n": 1, "WOrk\n": 1, "CC\n": 1, "Chris\n": 1, "Lode\n": 1, "Calf\n": 1, "CAREVEL\n": 1, "Paris\n": 1, "Subject Asergon\n": 1, "Cerzan\n": 1, "Interpol CARAVEL\n": 1, "Paris Interpol Hdqtrs\n": 1, "Ohenso B\n": 1, "Lscat\n": 1, "Neon\n": 1, "Cole Sep\n": 1, "Pte\n": 1, "Foran\n": 1, "Dare\n": 1, "Ofticer Crne\n": 1, "TTR\n": 1, "Subject US\n": 1, "Geraany\n": 1, "US\n": 1, "Colucbian\n": 1, "Subject Bovt\n": 1, "Subject Columbian\n": 1, "Soviet Columbian Sovs\n": 1, "Tong\n": 1, "Subject Soviet Columbian\n": 1, "Sovs\n": 1, "CO\n": 1, "Loox\n": 1, "German German GeFecroR\n": 1, "Ay\n": 1, "Bea Gosesberg\n": 1, "Maren\n": 1, "Gernany\n": 1, "CRE\n": 1, "South America Hien1 Apblicant\n": 1, "FKandate\n": 1, "Mandate\n": 1, "He\u00e9s\n": 1, "Te\n": 1, "Suppl\n": 1, "ICEM\n": 1, "ICEM Ieee\n": 1, "Tne BPR LP\n": 1, "OE\n": 1, "ICEM ICEM\n": 1, "USEP\n": 1, "ICFM\n": 1, "Linnnr\n": 1, "Bat\n": 1, "SOUrCES\n": 1, "Sad\n": 1, "ICEM ICF\n": 1, "ICEM ICEM Placement Service\n": 1, "Soutn\n": 1, "Tne\n": 1, "American JOtM\n": 1, "EE\n": 1, "Americas\n": 1, "Basic Seaniih\n": 1, "sKoald\n": 1, "Germar\n": 1, "aniLeast\n": 1, "Hotrs\n": 1, "Heegard\n": 1, "CEM\n": 1, "Ferope\n": 1, "South Americas\n": 1, "GouuNBia\n": 1, "-technician\n": 1, "South America Lawyers\n": 1, "Laborer\n": 1, "Lire\n": 1, "Housnig Liet\n": 1, "SORES\n": 1, "VER\n": 1, "AUS\n": 1, "S33 FeEM\n": 1, "LEWTAR Gewsve\n": 1, "CONTACT DEFZCTOR\n": 1, "French Subject\n": 1, "Subject INTZRFOL Eurcpean\n": 1, "France Subject\n": 1, "American South\n": 1, "Union Soviet\n": 1, "BEBe\n": 1, "Subject Doe\n": 1, "Keio\n": 1, "WIROGUE TeEnte\n": 1, "aY\n": 1, "Security\n": 1, "Yarouach\n": 1, "Grey\n": 1, "Wajor\n": 1, "Blake\n": 1, "Peter\n": 1, "PIO\n": 1, "Regis\n": 1, "USEP Cox\n": 1, "Barverd\n": 1, "Jack\n": 1, "BALL\n": 1, "Soot\n": 1, "So\n": 1, "Bill\n": 1, "Don Wel\n": 1, "Earl Brake Cox\n": 1, "RES\n": 1, "ANCONGEN\n": 1, "Blake South Aderica\n": 1, "ICEN\n": 1, "Subject Blake\n": 1, "ICEM South\n": 1, "Subsect\n": 1, "SHEIK\n": 1, "Blake Blake Subject\n": 1, "Arny\n": 1, "ICEL\n": 1, "APaP\n": 1, "Blake USEP\n": 1, "ICEM Camp\n": 1, "APRF\n": 1, "ICEM USEF\n": 1, "-Suhwaler St\u00a5ass\u00e9\n": 1, "Case Otticer\n": 1, "Ton\n": 1, "Baltic\n": 1, "South America USEP\n": 1, "EN Tews\n": 1, "ICEM Start\n": 1, "Spanish\n": 1, "Subject Baltic\n": 1, "Meg\n": 1, "sOERT\n": 1, "Columbia\n": 1, "Subject USSP\n": 1, "Subject Volunteer\n": 1, "Columbia P\u00e9tug\u00e9e\n": 1, "De\n": 1, "Hdqtrs\n": 1, "Subje Meno\n": 1, "Consulate\n": 1, "South ICEM\n": 1, "HIROSUE\n": 1, "CEM Bad Codeadurg Cy\n": 1, "Bach\n": 1, "German CASO\n": 1, "Schmitz\n": 1, "Liaison Officer\n": 1, "Ret\n": 1, "Gerian\n": 1, "BFV Anerican\n": 1, "Cy Wy SCHMITZ\n": 1, "Mehlea\n": 1, "Se Concerning\n": 1, "SANDERS\n": 1, "Suly\n": 1, "SANDERS Anong\n": 1, "SANDERS Soviet Union\n": 1, "Soviet Soviet\n": 1, "East\n": 1, "Germany Tiflis\n": 1, "East Berlin\n": 1, "Subject East\n": 1, "SANDERS West\n": 1, "Berlin\n": 1, "SANDERS Possiple\n": 1, "BUNDESAMT\n": 1, "SCHEITZ\n": 1, "BoP\n": 1, "SANDERS By2te\n": 1, "SANDERS Oberursel\n": 1, "Westbe\n": 1, "Ostgleichen Tage\n": 1, "Antrag\n": 1, "USDienstatelle\n": 1, "Bei\n": 1, "Vernehmung\n": 1, "SANDERS SANDERS\n": 1, "Plucht\n": 1, "Peptnohne\n": 1, "Gruppe\n": 1, "Einer\n": 1, "UdSSR\n": 1, "Pourister\n": 1, "SBZ\n": 1, "Tiflia\n": 1, "Ootberlin\n": 1, "Angaben\n": 1, "Angeblich\n": 1, "Weise\n": 1, "Freunde\n": 1, "Veraochten\n": 1, "Rittetlung\n": 1, "SANDEE\n": 1, "Uberlass\n": 1, "YorLiegenden\n": 1, "Imjauftreg\n": 1, "SECRET Beaten\n": 1, "Grre\n": 1, "Daronr\u00e9\n": 1, "OFtTeer\n": 1, "perFo\n": 1, "aSsureddSubject\n": 1, "CO Coiu\n": 1, "Bol\n": 1, "Consulate Hamburg\n": 1, "SA\n": 1, "File\n": 1, "EIP\n": 1, "Ronn\n": 1, "ZTROGUE\n": 1, "Georg BeY\n": 1, "SHer\u00e9fore\n": 1, "Cam\n": 1, "ERT Tece Wor\n": 1, "S\u00e9cauaa\n": 1, "Bry\n": 1, "Catezo\n": 1, "SeC\n": 1, "Gernan\n": 1, "West\n": 1, "Sohmtis\n": 1, "COX\n": 1, "Co\n": 1, "Sta\n": 1, "CCA\n": 1, "Metler\n": 1, "AIS\n": 1, "BT\n": 1, "OCA BfV\n": 1, "San Tequent\n": 1, "OCA ACh\n": 1, "ALS\n": 1, "KUBARK BARE\n": 1, "Cea\n": 1, "Activity\n": 1, "RAS\n": 1, "CO bfV\n": 1, "Bry Med\n": 1, "Rtv\n": 1, "Willms\n": 1, "Chief\n": 1, "Schnidt\n": 1, "Servicto\n": 1, "Villes\n": 1, "UXIGSSS\n": 1, "Chi\u00e9f\n": 1, "Schaidt\n": 1, "Paronnat\n": 1, "Case Subject RET\n": 1, "Anvolved\n": 1, "Case WIROGUE\n": 1, "Support\n": 1, "Georgian HARVARD\n": 1, "Subject OER\n": 1, "WIROGUE America\n": 1, "ANP\n": 1, "Sola George List\n": 1, "WIROGUE MEWORANDUW\n": 1, "FOR\n": 1, "THE RECO\n": 1, "Magher\n": 1, "Wi\n": 1, "Consulate Lot\n": 1, "Gare\n": 1, "Ga-and\n": 1, "Subject Subject Yntia\n": 1, "Feceive\n": 1, "Case WIROGUE America\n": 1, "SR\n": 1, "South Officer\n": 1, "Case Case\n": 1, "BARS\n": 1, "SECRET Deter\n": 1, "Po\n": 1, "Cast OF Cffie\n": 1, "CREEL\n": 1, "RS Fo\n": 1, "Bee\n": 1, "Subject Case\n": 1, "Officer January OT Sa\n": 1, "SECRET BYARDts\n": 1, "ITH\n": 1, "WrROGUE\n": 1, "ORME K\n": 1, "DARONNAT Subject\n": 1, "SO\n": 1, "Ain\n": 1, "Bag Se\n": 1, "AMENORANDUN\n": 1, "THE RECS\n": 1, "WIROGUE Case Ofticer\n": 1, "George\n": 1, "Chuck Pettit\n": 1, "San _.\n": 1, "Transportation\n": 1, "Subjeces\n": 1, "Subject Bullock\n": 1, "Subject CID\n": 1, "SECRET trRoctE\n": 1, "Siibject\n": 1, "EEE\n": 1, "TET Fe\n": 1, "Main Prankfur\u00e9\n": 1, "Geore Sonar\n": 1, "Cherursel\n": 1, "Main\n": 1, "Bernhot\n": 1, "Sandera\n": 1, "ae5S\n": 1, "eeATE CIRCUL\n": 1, "NOTE\n": 1, "Rayan\n": 1, "Zaflowt\n": 1, "Grtawnnvem\n": 1, "Rage Gea\n": 1, "Joke\n": 1, "ULtie\n": 1, "Bahnhof\n": 1, "Rictssany ACT\n": 1, "Coonomarion\n": 1, "LOCATION\n": 1, "Bt\n": 1, "L_ap\n": 1, "ROUTINGSlSI\n": 1, "aFink\n": 1, "Frankfurt MEE\n": 1, "Cinelli\n": 1, "Fic\n": 1, "Messe\n": 1, "Herrn\n": 1, "Georg Sanders Frankfurt\n": 1, "Main Oberursel\n": 1, "CONPACT\n": 1, "Log From\n": 1, "Subject Subject Subject Subject Case\n": 1, "Ee\n": 1, "Congo\n": 1, "wiSh\n": 1, "Lo Case\n": 1, "HBS\n": 1, "SECRET RangedatLearustesTHES Petty\n": 1, "zNie\n": 1, "German South America\n": 1, "SECRET REPORT\n": 1, "WrROGUE Subject\n": 1, "South America Headquarters\n": 1, "Subject Subject Case Officer\n": 1, "Subject Case Officer Subject\n": 1, "Subject ETN\n": 1, "See Stun\n": 1, "Headquarters Step\n": 1, "Subject HY\n": 1, "NEE Subject\n": 1, "DAROmAT\n": 1, "Spread\n": 1, "Subject LAT\n": 1, "UN\n": 1, "coMMacT\n": 1, "WITH\n": 1, "WIROGUE Wilhelm Salzma\n": 1, "Subject Parkstr\n": 1, "Wilhelm Reichel\n": 1, "Patentanwal\n": 1, "Frankfurt/Main\n": 1, "Subject South America\n": 1, "South America Case\n": 1, "Case Officer John\n": 1, "South America Case Officer\n": 1, "Germany SECRET Loot\n": 1, "__\n": 1, "Case Officer D\n": 1, "Subject weexCase\n": 1, "South America Subject\n": 1, "Case Office\n": 1, "Case Officer Subject\n": 1, "HARVARD SA\n": 1, "Subjeet\n": 1, "SUPE\n": 1, "Saetrration\n": 1, "Gernan Georg\n": 1, "Pa Ne\n": 1, "Hohemarkstr\n": 1, "Sanders Subject\n": 1, "Subject Unfortun\n": 1, "Athy Sugject\n": 1, "CO Re\n": 1, "Bes\n": 1, "avDli\n": 1, "Geo\n": 1, "CO Suggestion\n": 1, "Soonest\n": 1, "APP\n": 1, "Wirogue\n": 1, "Camp King Gus Zand Jack\n": 1, "COicet\n": 1, "Private\n": 1, "Arc\u00e9ntina\n": 1, "Lo Lo\n": 1, "REPORTCN\n": 1, "AGOREDEF\n": 1, "Subject Subject Subject Subject Hdgtrs\n": 1, "Subject SA Argentine\n": 1, "Subject Consulates\n": 1, "APRP\n": 1, "Subject Al\n": 1, "ALJ\n": 1, "Sutjyect\n": 1, "Subject Chile Harvard\n": 1, "cO\n": 1, "Subj\n": 1, "Someplsce\n": 1, "Ee German Congo\n": 1, "CAL\n": 1, "SAmerican\n": 1, "South Geduid\n": 1, "REPORT Pye Uy\n": 1, "ALONE\n": 1, "EN Et\n": 1, "Gaon\n": 1, "WIROGUE REDSOX\n": 1, "Candidate\n": 1, "WIROGUE Fran\n": 1, "KUBARK KUB\n": 1, "UBARKy Supplie\n": 1, "Congo Subject\n": 1, "Stephen R. LACKLEN\n": 1, "Roscoe MOSIEN\n": 1, "Subject Subject DARONNAT\n": 1, "Subject Subject Frankfurt\n": 1, "South America Congo\n": 1, "HARVARD Deeds\n": 1, "Pte KUBARK\n": 1, "LACKLEN\n": 1, "RUE\n": 1, "PPE\n": 1, "AF Division\n": 1, "Tas\n": 1, "HARVARD COns\n": 1, "TES\n": 1, "Fremde\n": 1, "Subject Germany U.S.\n": 1, "Canada\n": 1, "Engla\n": 1, "Australian\n": 1, "Panaskhet\n": 1, "HARVARD HARVARD Subject\n": 1, "Germans\n": 1, "Congoles\u00e9\n": 1, "Congo CE\n": 1, "Coat\n": 1, "HARVARD South\n": 1, "Clarance\n": 1, "LEIBROCK\n": 1, "MKTOPAZ\n": 1, "Subject South America Germany\n": 1, "Subject East HARVARD\n": 1, "Berlin Spec\n": 1, "Subject Georgian Dece\n": 1, "CAVATA\n": 1, "David -R\n": 1, "ARD\n": 1, "OCA HARV\n": 1, "Bonnt\n": 1, "Subject Story\n": 1, "WIROGUE WIROGUE HARVARD\n": 1, "CABEZONE\n": 1, "AIS OCA\n": 1, "ATA\n": 1, "Ops\n": 1, "vArgentina\n": 1, "Europe\n": 1, "American Camp King\n": 1, "South America Subject Colombian\n": 1, "HARVARD Subject Subject\n": 1, "Intergovernmental Committee\n": 1, "European Migration\n": 1, "ICEM CoB\n": 1, "Munich CAMANTILLA\n": 1, "HARVARD European\n": 1, "South America ICEM\n": 1, "Security Bterviews\n": 1, "Possib Tity\n": 1, "CAMANTIL\n": 1, "LA\n": 1, "Federal\n": 1, "Case Officer HARVA\n": 1, "Subject South American\n": 1, "Subject South America HARVARD\n": 1, "Subject KUBAR K\n": 1, "HARVARD South America\n": 1, "South Americ\n": 1, "German IBEX\n": 1, "HARVARD Gerald\n": 1, "Chios\n": 1, "CABEZONE BESDINS\n": 1, "eSca\n": 1, "Fject\n": 1, "Turkey HARVARD\n": 1, "HAR\n": 1, "D\n": 1, "DARONDAD\n": 1, "Soe Othe\n": 1, "Rtosrev\n": 1, "Sean\n": 1, "GR\n": 1, "OF FRANK\n": 1, "SANDER S\n": 1, "FULL\n": 1, "DATE OF\n": 1, "Tiflis\n": 1, "Georgia Russian\n": 1, "Georgian Tbilisi\n": 1, "NATIONAL\n": 1, "USSR\n": 1, "Tiflis Church\n": 1, "USSR Fhe\n": 1, "SOCIAL\n": 1, "Soviet Society\n": 1, "Russia Geo\n": 1, "Menshevists\n": 1, "Ger\n": 1, "British Soviet Only\n": 1, "Georgia Soviet\n": 1, "BIRTH\n": 1, "El\u00e9etrote\n": 1, "Engeneur\n": 1, "German KAYAtrician\n": 1, "Street Staveli\n": 1, "Nina\n": 1, "GANDELI\n": 1, "Georgian Was\n": 1, "Nina PARENTS\n": 1, "Franky SANDERS\n": 1, "Russia Baku\n": 1, "Batumi\n": 1, "Kind\n": 1, "Tbilisi\n": 1, "Baltic Thilisi\n": 1, "Maria SANDERS\n": 1, "Aze\n": 1, "Oblast\n": 1, "Tbilisi Was\n": 1, "Las\n": 1, "Cartel\n": 1, "ThAlist\n": 1, "FRIENDS\n": 1, "Georgian Rayon\n": 1, "RTS\n": 1, "SPECTAL\n": 1, "SKILLS\n": 1, "Georgian Russian\n": 1, "Russian English\n": 1, "Rustavi\n": 1, "Technicun\n": 1, "Germany Germany\n": 1, "None\n": 1, "NOt\n": 1, "Shko\n": 1, "Se\n": 1, "HANOVA\n": 1, "Georgian Russian Elektro\n": 1, "Tbhilisi\n": 1, "Sovets\n": 1, "_In\n": 1, "Auge\n": 1, "Ph\n": 1, "School\n": 1, "School Physics\n": 1, "English\n": 1, "Georgian Russian Soviet Union\n": 1, "School Fears\n": 1, "Bears\n": 1, "Nor\n": 1, "Ju\n": 1, "Summer\n": 1, "New\n": 1, "Semester\n": 1, "Fe\n": 1, "Cte\n": 1, "Bos -Plokho\n": 1, "Gehien\n": 1, "Jt\n": 1, "Repair\n": 1, "Technical Tekhnicheskaya\n": 1, "Stantsiya\n": 1, "Georgian Tskhakaya\n": 1, "Tskhakayskiy\n": 1, "Mikha Tskhakaya\n": 1, "Tskhakaya\n": 1, "Georgian Communist Party\n": 1, "RR\n": 1, "Samtred\n": 1, "Tb1lis\n": 1, "Moscow\n": 1, "Poti\n": 1, "Black Sea\n": 1, "Rion Rivers\n": 1, "Tsivi\n": 1, "Mikha Tskhakaya Josey Rachines\n": 1, "S\n": 1, "Ponsible\n": 1, "Kut\n": 1, "Baku\n": 1, "BRANCH OF\n": 1, "SERVICE\n": 1, "Salyan\n": 1, "Iranian\n": 1, "Soviet Army\n": 1, "Salyan Baku\n": 1, "Mae\n": 1, "Operat\u00e9\n": 1, "MiTIS\n": 1, "ERVE\n": 1, "Vieng\n": 1, "CE Cte\n": 1, "Rayvoyenkomat\n": 1, "CHRONOLOGY OF\n": 1, "CHOKHA\n": 1, "Major Vlado\n": 1, "Vladimir\n": 1, "GURGENIDZE\n": 1, "OZAD\n": 1, "PVO\n": 1, "VAKS\n": 1, "ENDELADZE\n": 1, "Michurin\n": 1, "Konskoye\n": 1, "Wher\n": 1, "Michurinsk\n": 1, "Kochetovka\n": 1, "SF\n": 1, "Michurinsk Juni\n": 1, "Comm\n": 1, "GURGENIDZE Aater\n": 1, "Lt\n": 1, "Six\n": 1, "Sergeant\n": 1, "Michurinsk Service\n": 1, "RESIDENCES\n": 1, "Tbilisi Le\n": 1, "Ulitsa Sovetskaya\n": 1, "Tskhakaya Tbilisi Ulitsa\n": 1, "Tsulukidze\n": 1, "Switchnan\n": 1, "LORDKIPANIDZE\n": 1, "Ilya\n": 1, "Keto\n": 1, "Catherine\n": 1, "CFs\n": 1, "Arity S\u00e9xvice\n": 1, "Mikta\n": 1, "Austaveli\n": 1, "Gants\n": 1, "ELI\n": 1, "Tfound\n": 1, "Ninang\n": 1, "Oppos\n": 1, "Nina Being\n": 1, "Nina Nina\n": 1, "USSR Nina\n": 1, "Nina Iwas\n": 1, "Georgian MEMBERSHIP\n": 1, "PAR\n": 1, "Communist Party\n": 1, "Komsomol\n": 1, "Tbilisi Komsomol\n": 1, "Komsomol Konsomol\n": 1, "Tbilisi Tbilisi\n": 1, "Mikha\n": 1, "Tskhakaya Tskhakaya\n": 1, "MTS\n": 1, "Cee CONNECTIONS\n": 1, "INTELLIGENCE\n": 1, "Soviet Organs COP\n": 1, "Communist\n": 1, "Communist USSR\n": 1, "wheIre\n": 1, "TECHNIQUES OF\n": 1, "Imet\n": 1, "Western\n": 1, "Samtredia\n": 1, "Samtredia Batumi\n": 1, "peOn\n": 1, "Batumi Turki\n": 1, "Russia Spent\n": 1, "Bettin\n": 1, "Shore\n": 1, "Sarpi\n": 1, "Soviet Russia\n": 1, "Spent\n": 1, "M\u00e9anwhile\n": 1, "Russia L\n": 1, "T\n": 1, "Erzerum\n": 1, "Istanbul\n": 1, "Germany DOCUMENTS\n": 1, "OF Oe\n": 1, "US Molotovskiy\n": 1, "Tbilisi Mikha Tskhakaya\n": 1, "F\n": 1, "Trudova\n": 1, "MT\n": 1, "CN\n": 1, "CO Fran FQ\n": 1, "Rec\n": 1, "Ce\n": 1, "Syiqen\n": 1, "RELY Neetu Rr\n": 1, "Bsbeee\n": 1, "Titre Ty\n": 1, "OO Mh\n": 1, "OCI\n": 1, "Subject Minor\n": 1, "Casehim\n": 1, "Leopoldville\n": 1, "Subject Subjecs\n": 1, "Subject Case Officer Subject Suoject\n": 1, "Headquarters Pepe\n": 1, "LEE\n": 1, "CONTACT wIROGUE Sos\n": 1, "Ostendsti\n": 1, "Josep LORTON\n": 1, "Subject Various\n": 1, "See Panaskhet\n": 1, "Derseind\n": 1, "Subject Subject Pusiness\n": 1, "Subject Subject Subject Headquarters\n": 1, "Subject Austrian\n": 1, "Zurope\n": 1, "SS3N\n": 1, "eaSs\n": 1, "Gee\n": 1, "nesSubse\n": 1, "Berd\n": 1, "Looe\n": 1, "REPORT Boy\n": 1, "JOs\n": 1, "Casey Officer\n": 1, "Mir\n": 1, "Subject Dur\n": 1, "Congo West\n": 1, "German POE\n": 1, "Congoleg\n": 1, "Subject Subject David\n": 1, "Panaskhet Could\n": 1, "Pana\n": 1, "Subject Subject France\n": 1, "Subject David\n": 1, "Panaskhe\n": 1, "Subject HARVARD SECRET\n": 1, "Comite\n": 1, "Teuhe\n": 1, "REPORT WS\n": 1, "Stephen\n": 1, "LAGUIEN\n": 1, "uTROGUE\n": 1, "-10d'Hours\n": 1, "LACKEY\n": 1, "Loanad\n": 1, "WIROGUE Frankfurt\n": 1, "LACKLEN KIROGUE\n": 1, "MOSIEY\n": 1, "WIROGUB\n": 1, "Dortmind\n": 1, "Dusseldorf\n": 1, "WIROGUE Washington\n": 1, "WIRCGUE\n": 1, "Austrian\n": 1, "Germany WIROGUE\n": 1, "Austrian WIROGUE\n": 1, "Bemg\n": 1, "Congo US\n": 1, "LACKLEN LACKLEN\n": 1, "WIROGUE Germany\n": 1, "LACKLEH\n": 1, "Germin\n": 1, "LACKLEN toWiest\n": 1, "Germany LACKLEN\n": 1, "WIR\n": 1, "German Congo\n": 1, "Loe\n": 1, "Austrian Congo\n": 1, "Congo LASKLEN\n": 1, "LACKLEN French\n": 1, "Congo LACKLEN\n": 1, "WIROGUE WIROGUE WashinBua\n": 1, "KUBARK LACKLEN\n": 1, "wWIROGUE\n": 1, "KUBARK German\n": 1, "David Da\n": 1, "Pinasktiot\n": 1, "WIRCGUE French\n": 1, "WIROGUE Baten\n": 1, "WXEEGE\n": 1, "WIROGUE LACKLEN\n": 1, "MOSIEN\n": 1, "Washington\n": 1, "WIROGUS\n": 1, "LACKLEN Program\n": 1, "LACKLEN SST\n": 1, "HORDer\n": 1, "Satna\n": 1, "Frankaon\n": 1, "Mr. Miller\n": 1, "LACKIEN\n": 1, "Main Bah\n": 1, "Aotin\n": 1, "TLACKIEN\n": 1, "WIROGUE WIRQGUS\n": 1, "Prankfurt\n": 1, "DOOS\n": 1, "LACKLEN CABEZONE\n": 1, "WIROGUE Hotel Savoy\n": 1, "LACKLEN Siv\n": 1, "Stephen R\n": 1, "Mr. Edward Miller\n": 1, "Rosoos MOSIEN\n": 1, "Mr. Dale\n": 1, "CANEZONE\n": 1, "WIROGUE Mr. Solneider\n": 1, "HURDWIN\n": 1, "Annex A Guard Post\n": 1, "Northern\n": 1, "WIROGUS Kis\n": 1, "LACKLEN LACKLEN LACKIEN\n": 1, "Bone\n": 1, "WEROGES\n": 1, "Ministry\n": 1, "Defense\n": 1, "Ywiss\n": 1, "Crder\n": 1, "LACKLAN\n": 1, "Congolese\n": 1, "Europe Prankfurt\n": 1, "WIROGUS Congo\n": 1, "Genera\n": 1, "Mobutu\n": 1, "American WIROQUE\n": 1, "LACKIGN\n": 1, "WIROGUS Belgian\n": 1, "Viennese WIRGGUE\n": 1, "Laopoldville\n": 1, "WIRCGUE Austrian\n": 1, "De Surete\n": 1, "Defense Ainlatry\n": 1, "nO\n": 1, "Goungolese\n": 1, "jJod\n": 1, "LACKLEN WIROOUE\n": 1, "LACKLEN WIROOUS\n": 1, "Germans France\n": 1, "LACKIZ\n": 1, "Congolese Government\n": 1, "Francs\n": 1, "Ke\n": 1, "Congolese Air Force\n": 1, "Pots\n": 1, "WIROGUB Passport\n": 1, "Return Be\n": 1, "Austrian Air Ticket\n": 1, "Leopoldville Pormit\n": 1, "Carte\n": 1, "Indenitite\n": 1, "Teohnioian\n": 1, "Status\n": 1, "Civilian\n": 1, "Health Certificate\n": 1, "Pass Congo\n": 1, "Passer\n": 1, "Ce Brazzatville\n": 1, "Eedesez Passer\n": 1, "Major\n": 1, "Hoyal Hetel\n": 1, "Vecoination\n": 1, "Missicn\n": 1, "Foreign Ministry Ordor\n": 1, "Army Brazzaville\n": 1, "Technician\n": 1, "Attache Kalongo\n": 1, "LACKIEN LACKLEN\n": 1, "WIROGUE Ahem\n": 1, "Lee\n": 1, "wIRGUUE\n": 1, "Array\n": 1, "See WINOGUE\n": 1, "WIRGGUE\n": 1, "Cons\n": 1, "WIROQUL\n": 1, "Army Germ\n": 1, "WIROGUE Soviet Russias\n": 1, "Congolose\n": 1, "LACKLEN RYBAT\n": 1, "WIROGUE WIROGUE WIROGUES\n": 1, "LACK\n": 1, "WIROQUE\n": 1, "Bend\n": 1, "Washington WIROGUE\n": 1, "Amportant\n": 1, "WIROGUE FRAN O404\n": 1, "DIR\n": 1, "LACKLEN WIRQQUE\n": 1, "DCOS\n": 1, "LACKLEN DIR Vand\n": 1, "MRTOPAZ\n": 1, "LEOP\n": 1, "Razsx\n": 1, "CABEZONE CREPE\n": 1, "LACKLEN PRANK\n": 1, "VORA\n": 1, "BNE\n": 1, "Prank SANDERS\n": 1, "Mutt\n": 1, "Abkiirzung\n": 1, "Zhori\n": 1, "Freunde Tiflis\n": 1, "Georgien\n": 1, "USSR Nane\n": 1, "Georgier\n": 1, "Bel GEBURT\n": 1, "Russland\n": 1, "Georgi\n": 1, "Pall\n": 1, "Truppen Resimes\n": 1, "Georgien Sowi\n": 1, "Macht\n": 1, "Jedoch\n": 1, "Personen\n": 1, "Sowje\n": 1, "Cy\n": 1, "Orthodox\n": 1, "Nein Vater\n": 1, "Mutter\n": 1, "COE\n": 1, "Deutsch\n": 1, "LETZTE\n": 1, "Lebensgefdhrtin\n": 1, "Krieg\n": 1, "Dorf Zu\n": 1, "Eltern\n": 1, "Nina Zeitpunkt\n": 1, "Eltern Bauern\n": 1, "Plucht GANDELI\n": 1, "SSR Strasse\n": 1, "Georgien -Seit\n": 1, "GANDELI TAKPASCHWILI\n": 1, "Oblast Nina\n": 1, "Elektriker ZCHAKAJA Sdpta Rustaveli\n": 1, "Kutaisi\n": 1, "Cnef MICHAL\n": 1, "Kann\n": 1, "Frank\n": 1, "Simon Baltikum\n": 1, "Gebiet\n": 1, "Baku Batumi\n": 1, "Tbilisi Gebiet\n": 1, "Arbeitsunfalls\n": 1, "Vater\n": 1, "Mutter Hann\n": 1, "Maria\n": 1, "SANDERS KANTSCHELT\n": 1, "Grenze\n": 1, "Tbilisi Oblast\n": 1, "Kind Eltern\n": 1, "Tbilisi Arbei\n": 1, "Unternehmungen\n": 1, "Biiros\n": 1, "Nachdem\n": 1, "Male\n": 1, "Verwandten\n": 1, "Heimatdorf\n": 1, "Koptakt\n": 1, "Familie\n": 1, "Ich\n": 1, "Ehe NAHE FREUNDE\n": 1, "Freunde Ich\n": 1, "Stadt\n": 1, "Direktor\n": 1, "Von RTS\n": 1, "SSR Rayon\n": 1, "Klinik Rayon\n": 1, "BESONDERE Rayons\n": 1, "Bibliothekarin\n": 1, "Rustavi Biro\n": 1, "Ich Klubs\n": 1, "Bauern\n": 1, "Heim\n": 1, "Personen VIEI\n": 1, "Schkola Nr\n": 1, "Tbiliai\n": 1, "Schule\n": 1, "Michailow\n": 1, "Zur Zeit\n": 1, "Rea\n": 1, "Trudowaja\n": 1, "Strassen PLECHANOV\n": 1, "Ulitsa Z\n": 1, "Stunden\n": 1, "Deutsch Georgier\n": 1, "Bis\n": 1, "Sprache\n": 1, "Sprach\n": 1, "Stunde\n": 1, "Ich Sieben Jahre\n": 1, "Scenule\n": 1, "Konnte\n": 1, "_Schule\n": 1, "NCAT\n": 1, "VAT\n": 1, "Vier Jahre\n": 1, "Verfassung Stand\n": 1, "Sowjet\n": 1, "Schule Systen\n": 1, "Dann Unterrichtsgegenstiin=.Mechanik\n": 1, "Messinstrum\u00e9nte\n": 1, "Zeichnen\n": 1, "Gruppe Sommerferien Kolchos\n": 1, "Union Metalle\n": 1, "Geschichte\n": 1, "Literatur\n": 1, "Methematik\n": 1, "Hcheren\n": 1, "Physik\n": 1, "Sprache T\u00e9chnikun\n": 1, "Englisch\n": 1, "Ernte\n": 1, "Jahre\n": 1, "Technikun\n": 1, "Semesters\n": 1, "Noten\n": 1, "WT\n": 1, "Posredstienno\n": 1, "QSAR\n": 1, "Art\n": 1, "Jahre Geldes\n": 1, "Regierung\n": 1, "Ausbildung\n": 1, "Ich BERUFLICHER\n": 1, "Flucht ZCHAKAJA\n": 1, "MICHA\n": 1, "Bev\u00e9lkerung\n": 1, "Zchakajskii Rayon\n": 1, "Stanzi\n": 1, "Zchakaja\n": 1, "M11\n": 1, "Revolutionir MICHA ZCKAKAJA\n": 1, "ACHAL\n": 1, "SENAKSKII Organisatoren Rayon\n": 1, "Zchakaja Parted\n": 1, "SHAR\n": 1, "TpAlisa\n": 1, "Abzweigungen\n": 1, "Bei Reparatur\n": 1, "Cube\n": 1, "Ele\n": 1, "Armee\n": 1, "Gehalt\n": 1, "Steliung Rayon\n": 1, "Rrieg Ich\n": 1, "Grundgenalt Stelle\n": 1, "ungefEhr\n": 1, "Vor\n": 1, "Ich Einwohrer\n": 1, "Stadt Brutto\n": 1, "Arbeitskrirten\n": 1, "Ich Re\n": 1, "Stelle\n": 1, "Schicht\n": 1, "Radios\n": 1, "Techrikums Stadt\n": 1, "Ich Griinden\n": 1, "Milit\u00e9rdienst\n": 1, "Ich Aus\n": 1, "Teile Pee\n": 1, "Ich Mit\n": 1, "Gruppe Zug\n": 1, "Tbilisi Sal\n": 1, "De Kasarmi\n": 1, "Gruppe Strasse\n": 1, "Grenze EINHEIT\n": 1, "Ich Artillerie\n": 1, "Eine Erkenriungsnunmer\n": 1, "Armee GRUNDAUSBILDUNG\n": 1, "Baku Baku\n": 1, "Einen Monat Nonat\n": 1, "Meine\n": 1, "Saljani\n": 1, "Kaserne\n": 1, "Baku Ausbildung\n": 1, "CoE\n": 1, "Soldbuch\n": 1, "Ubung\n": 1, "Militurdienst\n": 1, "Reserve\n": 1, "MSINES\n": 1, "Rekruten\n": 1, "Luftabwehr Art\n": 1, "illePie\n": 1, "Batterie\n": 1, "Batterie Ma\n": 1, "Wadicir\n": 1, "OSAD\n": 1, "Verwaltung\n": 1, "GURGENIDSE\n": 1, "Zugsfiihrer Senior\n": 1, "Haurcmann Leuznans\n": 1, "SAMARIN\n": 1, "WAXS\n": 1, "Stellvertretender Belange\n": 1, "Leutnant\n": 1, "Leutnant Batterie\n": 1, "Der\n": 1, "CENDELADSS\n": 1, "Einfluss\n": 1, "Georgier Di\n": 1, "Pahrer\n": 1, "GU2GLNIDSS\n": 1, "Oberstleutnant Er\n": 1, "Hilitdrdienst\n": 1, "Pou\n": 1, "Miliwurde\n": 1, "Gefreiten\n": 1, "Zum Unt\u00e9rfeldwed\n": 1, "Ende\n": 1, "Reisegeld\n": 1, "Ich Milit\u00e9rd\n": 1, "Ich Michurinsk\n": 1, "oPfiziell\n": 1, "WoHNOaTE\n": 1, "Seip\n": 1, "Sowjetaraja\n": 1, "Niimner\n": 1, "Erinnerung\n": 1, "Studentenhein\n": 1, "Tbilisi MICHA Hier\n": 1, "ZCHAKAJA\n": 1, "Ulitsa\n": 1, "Tsulukidse Zimmer\n": 1, "Haus\n": 1, "I1ja\n": 1, "LORDAIPANIDSE\n": 1, "Ilja\n": 1, "Frau Keto\n": 1, "Katherina Waische\n": 1, "Kinder\n": 1, "Ehepaar\n": 1, "Plucht Micha Zchnkaja\n": 1, "Uiitaa Schota Rustaveli Kr\n": 1, "Nina Celieds\n": 1, "Verhiltnia\n": 1, "Nina Hause Jahre\n": 1, "Abwesenheit\n": 1, "Minnern\n": 1, "Ich USSR\n": 1, "Ich Regierung\n": 1, "Plucht Bemerkungen Nachdem\n": 1, "Prauen\n": 1, "Nina Militia\n": 1, "Grinden\n": 1, "Nina Anschuldigung Informationen\n": 1, "Ich Teils\n": 1, "Militia\n": 1, "Sinne\n": 1, "Gelegenheiten\n": 1, "Nach\n": 1, "Einzelheiten\n": 1, "Militurdienst Verhtren\n": 1, "Militia Ausnahme\n": 1, "Militia Sicherheitsbehorden\n": 1, "MITGUBDSCHAPE Ich\n": 1, "Komsomol PARTS\n": 1, "ORGANISATIONEN\n": 1, "Tbilisi Bevolkerung\n": 1, "Armee MTS\n": 1, "MiT Entlassung\n": 1, "Z\u00e9it\n": 1, "EINEM\n": 1, "Vorteilen\n": 1, "Ich Kontakt\n": 1, "Ich Gewerkschaft\n": 1, "Beitriige\n": 1, "Gehaltes\n": 1, "Dasselbe\n": 1, "Ausstreichen\n": 1, "Art PDE\n": 1, "Hatten\n": 1, "Wahrheit\n": 1, "Mir Militia\n": 1, "Male Meine\n": 1, "Fluchtpl\u00e9ne\n": 1, "Ausdruck Entwicklung\n": 1, "Zeit\n": 1, "USSR Nachdem\n": 1, "Lange\n": 1, "Familie Radio Lander\n": 1, "Lage\n": 1, "Erfahrung\n": 1, "Batumi Batumi\n": 1, "Ich Seeufers\n": 1, "Wasser\n": 1, "Kleider\n": 1, "Pass\n": 1, "Tasche\n": 1, "Fuss\n": 1, "Ich Hause\n": 1, "Studiiam\n": 1, "Landkarte\n": 1, "Gebiet Ich\n": 1, "Ufer Hiitte\n": 1, "Gebiet Punkt\n": 1, "Ich Silhuette\n": 1, "Russland Ich\n": 1, "Nihe\n": 1, "Ufer\n": 1, "Teh\n": 1, "Morgen Gebilde\n": 1, "Offnung\n": 1, "Ufernihe\n": 1, "Steinernes Sah\n": 1, "Ich Abhang\n": 1, "Schaute\n": 1, "Hohle\n": 1, "Morgen\n": 1, "Grab\n": 1, "Umgebung Sah\n": 1, "Dorf\n": 1, "Ich Dorf Sarpi\n": 1, "Boden\n": 1, "Ich Hiigel\n": 1, "PAVY\n": 1, "Sttick Ich\n": 1, "Ich Bach Dann\n": 1, "Dunkeiheit\n": 1, "Ende Buben\n": 1, "Dorf Abhang\n": 1, "Ich Dorf\n": 1, "Hause\n": 1, "Hugels\n": 1, "Ich Pate\n": 1, "Tafel Nylonsack\n": 1, "Wasser Krampfes\n": 1, "Schockolade\n": 1, "Tabletten\n": 1, "Girtel\n": 1, "Nadeln\n": 1, "Energie Mit Ausnahme\n": 1, "Tauchen\n": 1, "Geld Kompass\n": 1, "Hindernii\n": 1, "Von Kemal-Pascha\n": 1, "Wagen\n": 1, "Erserum\n": 1, "Kleider Istanbul\n": 1, "Fliichtlingslager\n": 1, "Dort\n": 1, "Woche\n": 1, "Hilfe\n": 1, "US Behtrden\n": 1, "Freitag\n": 1, "Deutschland\n": 1, "Ich Jahre\n": 1, "Teh Pass\n": 1, "Russo\n": 1, "Stinson\n": 1, "Entlassung\n": 1, "Daraug\n": 1, "Pass Siehe\n": 1, "Para\n": 1, "Adresse\n": 1, "Bilet Infier Armee\n": 1, "Pass Dienststelle\n": 1, "Trudowa\n": 1, "Knishka_\n": 1, "Entlassung ARBEITSBUCH\n": 1, "Ich Wojenrii\n": 1, "Pass Ich\n": 1, "F ER\n": 1, "Se atE\n": 1, "Sehr\n": 1, "Kerr\n": 1, "Generalkonsuli Oe\n": 1, "Im\n": 1, "Auswanderung\n": 1, "Ich Ihnen\n": 1, "Dank\n": 1, "Sie\n": 1, "Yorgang\n": 1, "Frwerbung\n": 1, "Mustern Saemtlicher\n": 1, "Fragee\n": 1, "Anzahl\n": 1, "Chile Finschraenkungen\n": 1, "Hinaicht\n": 1, "Welche Benife\n": 1, "Muss\n": 1, "Fimanderer\n": 1, "Hinsicht\n": 1, "Frteilung\n": 1, "Auskuenfte\n": 1, "Jhnen\n": 1, "Mit\n": 1, "Rochachtung A\n": 1, "QO\n": 1, "Elnendort\n": 1, "Consulate Viea\n": 1, "Circular\n": 1, "Cartilla\n": 1, "Spanisn\n": 1, "Ge\n": 1, "SAS\n": 1, "BarePF Cyan\n": 1, "PENG\n": 1, "Le Certain\n": 1, "RGB\n": 1, "Germany Trucks\n": 1, "SPAN\n": 1, "Chilean Consulate\n": 1, "Santiago\n": 1, "GENERAL DE\n": 1, "Russ\n": 1, "Chile Sekr\n": 1, "Eerren\n": 1, "Beantwortung\n": 1, "Fragen\n": 1, "Auusat\n": 1, "Ihnen\n": 1, "Auskunft\n": 1, "Gefragt Sind\n": 1, "Seite\n": 1, "Siehe\n": 1, "Circular Innen\n": 1, "Einwanderer\n": 1, "Ihrer\n": 1, "Verriigung\n": 1, "Eockachtung\n": 1, "Melkonigen Konsul Ce\n": 1, "Sabet\n": 1, "Freedom\n": 1, "viSacior\n": 1, "DE\n": 1, "ACION DE\n": 1, "RESIDSYTE\n": 1, "W1s\u00e9ciox\n": 1, "Wi3ACTOu\n": 1, "Auf Grind\n": 1, "Abkormens\n": 1, "Chile Aufente\n": 1, "Fillen\n": 1, "Lal\n": 1, "Chile Chile\n": 1, "Unterlagen\n": 1, "Pass Visum\n": 1, "Personr\n": 1, "Staatsarge\n": 1, "Beruf\n": 1, "Stempel\n": 1, "Unterschrift\n": 1, "Sowie\n": 1, "Lichtbild\n": 1, "Auferdem\n": 1, "Internationel\n": 1, "Pockeninpfschein\n": 1, "Gliltig\n": 1, "Bei Riickpassa\n": 1, "Tourist\n": 1, "Chile Ger Toiris\n": 1, "Chile Tourist\n": 1, "Ausnahz\n": 1, "Chile Cene\n": 1, "Schstiauer\n": 1, "Chile CIO DE\n": 1, "LTTS\n": 1, "Personen Erholungsreisende\n": 1, "Vatigkeit\n": 1, "Fell\n": 1, "Arbeitrencters\n": 1, "Jes\n": 1, "Recht\n": 1, "Kosten\n": 1, "Bei Vertragsende\n": 1, "Pernanencia Definitiva\n": 1, "Die Visumgebiihren IIl\n": 1, "VISACION\n": 1, "DE Resiogn Ts Sehdrden\n": 1, "Visuc Visum\n": 1, "Visum\n": 1, "Aus Land\u00e9rn\n": 1, "Fachschilen\n": 1, "Der Inhaber\n": 1, "Visuns\n": 1, "Chile Zscist\n": 1, "Dauervisum Kat\n": 1, "Ta\u00e9tigkeit Usist\u00e9nden\n": 1, "Genehnisung\n": 1, "Lend Visuns\n": 1, "Chile Mach\n": 1, "Chile Recht\n": 1, "Die Visungebihhren\n": 1, "VISAC\n": 1, "RESTVENTS\n": 1, "Visua\n": 1, "Visum Chile\n": 1, "KOZEEN\n": 1, "S3ehorden\n": 1, "daG\n": 1, "Aus\n": 1, "Chile Aufenthalt\n": 1, "Chile Rach\n": 1, "Inhater\n": 1, "Visuzms\n": 1, "Jareraxfenthaltsgene\n": 1, "Chile Definitiva\n": 1, "Jahr\n": 1, "Visurerteilung\n": 1, "IENTE\n": 1, "Ehefrau\n": 1, "Visa _Siof\n": 1, "TEPORARIO\n": 1, "Bedi\n": 1, "Insbeso\n": 1, "Circular Nr.3\n": 1, "Cartill\n": 1, "Konsulat\n": 1, "Ausfertigung\n": 1, "Maschine\n": 1, "Die Visungebithren\n": 1, "Bei Gepickliste\n": 1, "Wenn\n": 1, "Visum Solgendes\n": 1, "Erteilung\n": 1, "Visuns Eigentu\n": 1, "Eerkunfis\n": 1, "Ausnahmefillen\n": 1, "Visumerteilung\n": 1, "Vis\n": 1, "Visumerteilung Bedarf\n": 1, "Unter Gegenstanden\n": 1, "Einwanderungsvisun\n": 1, "Tatigkeit\n": 1, "Auswanderer\n": 1, "Deutschland Einwanderer\n": 1, "Es\n": 1, "Lastkraftwagen\n": 1, "Jeep\n": 1, "Tempowagen\n": 1, "Jeep Tempowagen\n": 1, "Lieferwagen\n": 1, "Personerwagen_\n": 1, "Fahrzeuge\n": 1, "Tatizkeit Musikschranke\n": 1, "Das Unzugsgut\n": 1, "Gobelins\n": 1, "Sind\n": 1, "Konsulat Inter\u00e9asenten\n": 1, "Wistiierteilan\n": 1, "Art Pers\u00e9niiche\n": 1, "Jahren\n": 1, "Obvohl\n": 1, "AuSerrir\n": 1, "Chilenigsche Generalkonsilat\n": 1, "Recht Riche\n": 1, "Visumarten\n": 1, "Fockeniny\n": 1, "Seine Giiltickeiisdauer\n": 1, "Beg\n": 1, "klErung\n": 1, "Vaters\n": 1, "Sane\n": 1, "Reise\n": 1, "Ausiand\n": 1, "Das Konsulat\n": 1, "Es Zeitu\n": 1, "Fir\n": 1, "CONDOR\n": 1, "Santiago Criericah\n": 1, "Fess\n": 1, "ER\n": 1, "AaSwand\u00e9run\n": 1, "Berlin Hanau\n": 1, "Nickt\n": 1, "Ariserzt\n": 1, "Kind biLeen\n": 1, "Dj\n": 1, "SONG\n": 1, "Gebiinren\n": 1, "Pragebogen\n": 1, "Tinte\n": 1, "Ausfertigung Untersciriever\n": 1, "Irhaitsaufstellung\n": 1, "Sprache Sprache\n": 1, "Urtercenrift\n": 1, "Reise Inren Beruf\n": 1, "Ausferticung\n": 1, "Maschine Schreibrasc\n": 1, "Vaters Chile Gurchgestrich\n": 1, "Aufenthalt\n": 1, "Zin Erziets\n": 1, "Auswanderungsprograzee\n": 1, "Fluec\n": 1, "Personen Auswanderung\n": 1, "Peru\n": 1, "Ihnen Sie\n": 1, "Yorgane\n": 1, "Frwerbung Finreisevisums\n": 1, "Fragebogen\n": 1, "Seifuegung\n": 1, "Anzahl Betre\n": 1, "Pera\n": 1, "Land\n": 1, "Gle EinwanZeruncsquote\n": 1, "Finschraenkungen\n": 1, "Welche\n": 1, "Musa\n": 1, "Finwanderer Geldmittein\n": 1, "Anforderurgen Wanuerers\n": 1, "Hinsicht Mindestsumme Yl\n": 1, "Entgegenkomnen\n": 1, "Frtetlung\n": 1, "Ihnen Auskuenfte\n": 1, "Yoracs\n": 1, "Mit Hoch\n": 1, "Guaolletts\n": 1, "Peru Travel\n": 1, "Birth\n": 1, "Medical\n": 1, "Consulate Peru\n": 1, "Paragraph\n": 1, "Peru derungSprogramns\n": 1, "Snteressiert\n": 1, "Teh Sie\n": 1, "Punkte\n": 1, "Vorgang\n": 1, "Fryerbung\n": 1, "Beif\n": 1, "Won Muster\n": 1, "Pragebogen Muss\n": 1, "Verfuegea\n": 1, "Mindestsumme Finwanderungsvisum\n": 1, "Gesuccheitezustand\n": 1, "Elnend\u00e9rt\n": 1, "Saye\n": 1, "Perscrien\n": 1, "Ich Sie\n": 1, "Auswande\n": 1, "Venezuela\n": 1, "Dank Punkte\n": 1, "Vorpang\n": 1, "Angahl\n": 1, "MUSSy\n": 1, "Frverbung\n": 1, "Finwamlerervisums\n": 1, "Licher\n": 1, "Fragebogen Betreffende\n": 1, "Venenaela Stantabuergerschaft Ihres Landes\n": 1, "Land Welehe Berufe\n": 1, "Hinsicht Muss\n": 1, "Finwanderer\n": 1, "Hinsicht Gesundheitszustan\n": 1, "Auskcenfte\n": 1, "Ihnen Hochachtung Ae\n": 1, "Lote\n": 1, "Prankfust\n": 1, "Setr\n": 1, "Herr Nonsala\n": 1, "Im Rahnen\n": 1, "Auswandersnzsorog\n": 1, "Persoren\n": 1, "Auswarderung\n": 1, "Ecuador\n": 1, "Ich Ihnen Punkte\n": 1, "Vorgang Finreisevisums\n": 1, "Beifuegung\n": 1, "Mustern\n": 1, "Frapebogen\n": 1, "Anzahl Feuador\n": 1, "Landes\n": 1, "Welehe S.\n": 1, "Muss Finwanderer\n": 1, "Land Fiinwanderongsquote\n": 1, "Hinaicht Berufe\n": 1, "Hinsicht Mind Jestsunme\n": 1, "Gesundkeitsaustand\n": 1, "Eine\n": 1, "Frted\n": 1, "Hochachtung A.\n": 1, "Personen Auswanderung Ich\n": 1, "Coos\n": 1, "Punkte Hinsicht\n": 1, "Berufe\n": 1, "Muss Geldmit\n": 1, "Gesundhestosustand\n": 1, "Entgefenkomzen\n": 1, "Ihnen Im Sahren\n": 1, "Auswaaierunzsor\n": 1, "Fluechtlinge\n": 1, "Paraguay\n": 1, "Jeh Waer\n": 1, "Dank Sie\n": 1, "Purkte\n": 1, "Vorgang Frverourg\n": 1, "Mustern Saeabiicher\n": 1, "Fragebocen\n": 1, "Anzahl Seifeegung\n": 1, "Staatsbuergexschsft Tnres\n": 1, "Paraguay Lond\n": 1, "Hinaicht Einwan\n": 1, "Berufe Sestirmty Mis\n": 1, "Pomwanteruagsvisua\n": 1, "Anforde\n": 1, "Fate\n": 1, "Auskuenfte Erteileng\n": 1, "Fochachtang Ae\n": 1, "Agraria\n": 1, "Institute\n": 1, "Higran\n": 1, "Sis\n": 1, "Fluecht Linge\n": 1, "Bolivien\n": 1, "Ich Dank\n": 1, "Punkte Erverbung\n": 1, "Licher Frage\n": 1, "Welche Muss Berufe\n": 1, "Finwanderer Dede CRG Oeldmitteln\n": 1, "Anford\n": 1, "Hinaicht Gepunine\n": 1, "Thren\n": 1, "Auskuenfte Ihnen Ministerio\n": 1, "Bolivien Tbak\n": 1, "Sie Hintsteriun\n": 1, "FY\n": 1, "Voakonioehe\n": 1, "Rshnen\n": 1, "Au\u00e9wand\u00e9run\u00e9sprograms\n": 1, "Personen Auswanderung Uruguay\n": 1, "Ich Ihnen Sie\n": 1, "Frwerbung Einreisevisums\n": 1, "Beifuegung Frage\n": 1, "Vorgang Anzahl\n": 1, "Finschraenkungen Land\n": 1, "Retreffende Staatsbuergerschaft\n": 1, "Uruguay\n": 1, "Hinsicht Muss Berufe\n": 1, "Finwanderer Gelunitteln\n": 1, "Fuer Anforderngen\n": 1, "Ihren Mindestsunmme Firwanderunzevisum\n": 1, "Gesundheitszustand\n": 1, "Frtei\n": 1, "Hochachtung Le\n": 1, "Elme\n": 1}